{"data":{"followers":[{"date":1648771200000,"value":228238703},{"date":1651363200000,"value":233653860},{"date":1654041600000,"value":238430514},{"date":1656633600000,"value":245914164},{"date":1659312000000,"value":252076319},{"date":1661990400000,"value":254662663},{"date":1664582400000,"value":259590267},{"date":1667260800000,"value":263594014},{"date":1669852800000,"value":266925021},{"date":1672531200000,"value":271827228},{"date":1675209600000,"value":275878626},{"date":1677628800000,"value":279413590},{"date":1680307200000,"value":284008968},{"date":1682899200000,"value":287846670},{"date":1685577600000,"value":290759947},{"date":1688169600000,"value":293394261},{"date":1690848000000,"value":292882861},{"date":1693526400000,"value":292994954},{"date":1696118400000,"value":292691212},{"date":1698796800000,"value":292779355},{"date":1701388800000,"value":292083902},{"date":1704067200000,"value":292028570}],"views":[],"increase_views":[],"increase_followers":[{"date":1651363200000,"value":5415157},{"date":1654041600000,"value":4776654},{"date":1656633600000,"value":7483650},{"date":1659312000000,"value":6162155},{"date":1661990400000,"value":2586344},{"date":1664582400000,"value":4927604},{"date":1667260800000,"value":4003747},{"date":1669852800000,"value":3331007},{"date":1672531200000,"value":4902207},{"date":1675209600000,"value":4051398},{"date":1677628800000,"value":3534964},{"date":1680307200000,"value":4595378},{"date":1682899200000,"value":3837702},{"date":1685577600000,"value":2913277},{"date":1688169600000,"value":2634314},{"date":1690848000000,"value":-511400},{"date":1693526400000,"value":112093},{"date":1696118400000,"value":-303742},{"date":1698796800000,"value":88143},{"date":1701388800000,"value":-695453},{"date":1704067200000,"value":-55332}]},"post_data":[{"date":1648771200000,"post":{"tiktok_post_id":null,"url":"https://www.instagram.com/p/Cb-7jhqlRbW","post_user_id":"5a3daafaedc29549b4bc3bd1","channel":"instagram","author":"justinbieber","created_at":"2022-04-05T20:46:25","title":"My witttle bum bum 📷: @alfredoflores","image_url":"https://s3-us-west-2.amazonaws.com/crawler.img/624d58b4eb68922c1bbd9e07.jpg","avatar":"https://scontent-sea1-1.xx.fbcdn.net/v/t51.2885-15/271177452_149300624107486_238439661515940835_n.jpg?_nc_cat=1&ccb=1-5&_nc_sid=86c713&_nc_ohc=OmCl8HOaZdcAX9P3iQl&_nc_ht=scontent-sea1-1.xx&edm=AL-3X8kEAAAA&oh=00_AT_4Wh7EL175IG_5CkfIi6bDXW7SvnDOe5lLdk3HRfGOaA&oe=62596AC2","content":null,"likes":5388288,"comments":16528,"is_business":true,"is_new":false,"clean":true,"last_update_time":"2022-06-02T22:50:34.443329","followers":238430514,"max_price":2546112,"min_price":1505677,"location_name":"","location_public":false,"is_video":false,"album":["https://instagram.fcgk19-1.fna.fbcdn.net/v/t51.2885-15/277886864_556129219026874_6062379888888816999_n.jpg?stp=dst-jpg_e35_p1080x1080&_nc_ht=instagram.fcgk19-1.fna.fbcdn.net&_nc_cat=110&_nc_ohc=hgaKfwNBgSMAX-T5cDz&edm=AABBvjUBAAAA&ccb=7-5&oh=00_AT_dGREiheqRPoYoLUFniJYFCVCWxOCOy1CJLiL4nxRB6g&oe=62A1012A&_nc_sid=83d603","https://instagram.fcgk19-1.fna.fbcdn.net/v/t51.2885-15/277909317_693784581743396_6093965609496897795_n.jpg?stp=dst-jpg_e35_p1080x1080&_nc_ht=instagram.fcgk19-1.fna.fbcdn.net&_nc_cat=108&_nc_ohc=XIT3AMmTS0IAX-apESu&edm=AABBvjUBAAAA&ccb=7-5&oh=00_AT9zu4pUOQmyt2mE0t6rIOOJhJFx6C6N7CbHyrfi0AtDzA&oe=629FB48F&_nc_sid=83d603","https://instagram.fcgk19-1.fna.fbcdn.net/v/t51.2885-15/277857519_1049459615654990_8386679441694224952_n.jpg?stp=dst-jpg_e35_p1080x1080&_nc_ht=instagram.fcgk19-1.fna.fbcdn.net&_nc_cat=102&_nc_ohc=cTZKW-iiKdUAX-2SXdG&edm=AABBvjUBAAAA&ccb=7-5&oh=00_AT8sg7aSFaK0lB5luRE2rWBI7nQ0bheW_wMqfkMH5nVngw&oe=62A0599D&_nc_sid=83d603","https://instagram.fcgk19-1.fna.fbcdn.net/v/t51.2885-15/277902041_301993748569017_5707015317061165259_n.jpg?stp=dst-jpg_e35_p1080x1080&_nc_ht=instagram.fcgk19-1.fna.fbcdn.net&_nc_cat=109&_nc_ohc=Gs-fxKZ8-CQAX97ZgnX&edm=AABBvjUBAAAA&ccb=7-5&oh=00_AT93P3YQLdZ67kBKKZqLLnT8We7lZhF2SU4Iipj7hBVWZQ&oe=62A08827&_nc_sid=83d603"],"location_slug":"","location_id":"","last_comment_ref":"17890111988634247","brand_mentions":[],"embedded_links":[],"top_comments":[],"sentiment_distribution":{"neg":0,"pos":0,"neu":0},"positive_comments":[],"demos_failed":true,"id":null}},{"date":1651363200000,"post":{"tiktok_post_id":null,"url":"https://www.instagram.com/p/CdE6gD5pPxv","post_user_id":"5a3daafaedc29549b4bc3bd1","channel":"instagram","author":"justinbieber","created_at":"2022-05-03T01:04:03","title":"🚀🚀🚀🚀🚀🚀🚀","image_url":"https://s3-us-west-2.amazonaws.com/crawler.img/62721bee0464cd0ffba94580.jpg","avatar":"https://scontent-sea1-1.xx.fbcdn.net/v/t51.2885-15/271177452_149300624107486_238439661515940835_n.jpg?_nc_cat=1&ccb=1-6&_nc_sid=86c713&_nc_ohc=hIWsPKpeEUwAX-F3BxJ&_nc_ht=scontent-sea1-1.xx&edm=AL-3X8kEAAAA&oh=00_AT9zlQHjYbp8lPBHsUvVl2wld29mCehgdKllFPzHN-_GSg&oe=627EFD82","content":null,"likes":3153003,"comments":11391,"is_business":true,"is_new":false,"clean":true,"brand_mentions":[],"embedded_links":[],"top_comments":[],"sentiment_distribution":{"neg":0,"pos":0,"neu":0},"positive_comments":[],"demos_failed":true,"last_update_time":"2022-06-30T07:05:03.953052","followers":245420967,"max_price":2546112,"min_price":1505677,"location_name":"","location_public":false,"is_video":false,"album":[],"location_slug":"","location_id":"","last_comment_ref":"17900418590607323"}},{"date":1654041600000,"post":{"tiktok_post_id":null,"url":"https://www.instagram.com/tv/CeorE9OjqX9","post_user_id":"5a3daafaedc29549b4bc3bd1","channel":"instagram","author":"justinbieber","created_at":"2022-06-10T18:55:48","title":"IMPORTANT PLEASE WATCH. I love you guys and keep me in your prayers","image_url":"https://s3-us-west-2.amazonaws.com/crawler.img/62a3b0b46b577b4a015deeca.jpg","avatar":"https://scontent-sea1-1.xx.fbcdn.net/v/t51.2885-15/271177452_149300624107486_238439661515940835_n.jpg?_nc_cat=1&ccb=1-7&_nc_sid=86c713&_nc_ohc=690YXp2LCQcAX-Yk4gu&_nc_ht=scontent-sea1-1.xx&edm=AL-3X8kEAAAA&oh=00_AT-uQtXKc5TGPvVR7B3qhcKdGrMy1sjpg43p6MtV37zK3Q&oe=632714C2","content":null,"likes":9385059,"comments":442480,"is_video":true,"is_business":true,"clean":true,"deleted":true,"inactive":true,"is_new":false,"last_update_time":"2022-09-14T22:28:19.511954","followers":255323581,"max_price":2546112,"min_price":1505677,"location_name":"","location_public":false,"video_url":"https://instagram.fanf1-1.fna.fbcdn.net/v/t50.16885-16/10000000_3266730926918740_5672625282024415581_n.mp4?efg=eyJ2ZW5jb2RlX3RhZyI6InZ0c192b2RfdXJsZ2VuLjcyMC5pZ3R2LmJhc2VsaW5lIiwicWVfZ3JvdXBzIjoiW1wiaWdfd2ViX2RlbGl2ZXJ5X3Z0c19vdGZcIl0ifQ&_nc_ht=instagram.fanf1-1.fna.fbcdn.net&_nc_cat=104&_nc_ohc=5wwJ0djENBcAX8kNSnq&edm=AABBvjUBAAAA&vs=832834268105466_1108916455&_nc_vs=HBksFQAYJEdJQ1dtQUJVekhrUUU1c0xBRjBoOTU2ak5ybE9idlZCQUFBRhUAAsgBABUAGCRHRlU5RmhIanpiRm50bE1FQU9LeExmS3FGUFIyYnZWQkFBQUYVAgLIAQAoABgAGwGIB3VzZV9vaWwBMRUAACbCt6vZi4rgPxUCKAJDMywXQGXGZmZmZmYYEmRhc2hfYmFzZWxpbmVfMV92MREAdewHAA%3D%3D&ccb=7-5&oe=632467D4&oh=00_AT_nIeCyN8NZGrRM1m2GM9iAlLITkUT4aGGdadE5Hs_f-Q&_nc_sid=83d603","album":[],"location_slug":"","views":64485964,"location_id":"","last_comment_ref":"17955374650900568"}},{"date":1656633600000,"post":{"tiktok_post_id":null,"url":"https://www.instagram.com/p/CfmgEdzv0mu","post_user_id":"5a3daafaedc29549b4bc3bd1","channel":"instagram","author":"justinbieber","created_at":"2022-07-04T19:10:03","title":"Love my nephew Ryver","image_url":"https://s3-us-west-2.amazonaws.com/crawler.img/62c4ad9591345e91a1a62154.jpg","avatar":"https://scontent-sea1-1.xx.fbcdn.net/v/t51.2885-15/271177452_149300624107486_238439661515940835_n.jpg?_nc_cat=1&cb=48425d84-f4de032c&ccb=1-7&_nc_sid=86c713&_nc_ohc=8UO9QiUA-XIAX89So51&_nc_ht=scontent-sea1-1.xx&edm=AL-3X8kEAAAA&oh=00_AT8I4MqfQfzEH4HjyoZDrL7j5ounrIQPpjv3HzstWahs2A&oe=62CA2302","content":null,"likes":4176525,"comments":16325,"is_business":true,"clean":true,"last_update_time":"2022-07-06T10:13:15.610958","followers":247000653,"max_price":2546112,"min_price":1505677,"location_name":"","location_public":false,"is_video":false,"album":[],"location_slug":"","location_id":"","last_comment_ref":"17853474239763152","brand_mentions":[],"embedded_links":[],"top_comments":[],"sentiment_distribution":{"neg":0,"pos":0,"neu":0},"positive_comments":[],"demos_failed":true,"deleted":true,"inactive":true}},{"date":1659312000000,"post":{"tiktok_post_id":null,"url":"https://www.instagram.com/p/ChMwCWyuH9V","post_user_id":"5a3daafaedc29549b4bc3bd1","channel":"instagram","author":"justinbieber","created_at":"2022-08-13T12:12:07","title":"📷: @rorykramer","image_url":"https://s3-us-west-2.amazonaws.com/crawler.img/62f82f0d39642420b6a1bc2c.jpg","avatar":"https://scontent-sea1-1.xx.fbcdn.net/v/t51.2885-15/271177452_149300624107486_238439661515940835_n.jpg?_nc_cat=1&ccb=1-7&_nc_sid=86c713&_nc_ohc=y9kRq_inJdMAX9Zsbek&_nc_ht=scontent-sea1-1.xx&edm=AL-3X8kEAAAA&oh=00_AfBgqcSwlUFTxiErOd_Jp_wC6J-mQDcKsKQmr79GeV1LJQ&oe=63C15442","content":null,"likes":5438702,"comments":23288,"is_business":true,"clean":true,"brand_mentions":[],"embedded_links":[],"last_update_time":"2023-01-11T05:19:29.986335","followers":273021660,"max_price":2546112,"min_price":1505677,"location_name":"","location_public":false,"is_video":false,"album":["https://instagram.fkhi22-1.fna.fbcdn.net/v/t51.2885-15/299114068_779499286430163_4118470731658875566_n.jpg?stp=dst-jpg_e35_p1080x1080&_nc_ht=instagram.fkhi22-1.fna.fbcdn.net&_nc_cat=103&_nc_ohc=M2LVZ99EH9EAX-QsWYV&edm=AABBvjUBAAAA&ccb=7-5&oh=00_AfBXNIWHKins-ovO0Fi0b5P90zG5ka2CC6sC4QHuYGxNWQ&oe=63C23F0E&_nc_sid=83d603","https://instagram.fkhi22-1.fna.fbcdn.net/v/t51.2885-15/298933174_624352612382060_1627188947766009580_n.jpg?stp=dst-jpg_e35_p1080x1080&_nc_ht=instagram.fkhi22-1.fna.fbcdn.net&_nc_cat=108&_nc_ohc=et5y5IOLc94AX8zbpFg&edm=AABBvjUBAAAA&ccb=7-5&oh=00_AfBAH21vtdJuAhg1XdvRyBBHTr3wajZogio0MDLbwy8Vqg&oe=63C2B247&_nc_sid=83d603","https://instagram.fkhi22-1.fna.fbcdn.net/v/t51.2885-15/298811127_1311252442738109_8784228853150621645_n.jpg?stp=dst-jpg_e35_p1080x1080&_nc_ht=instagram.fkhi22-1.fna.fbcdn.net&_nc_cat=105&_nc_ohc=ZWwVMd40kkYAX-6Mmhd&edm=AABBvjUBAAAA&ccb=7-5&oh=00_AfB2DyMRHuIWl4Kh7NiCNiBSwsnuH4fViQaElCIHBySxOg&oe=63C3A2F4&_nc_sid=83d603","https://instagram.fkhi22-1.fna.fbcdn.net/v/t51.2885-15/299101964_5368552689897851_7635570395895156317_n.jpg?stp=dst-jpg_e35_p1080x1080&_nc_ht=instagram.fkhi22-1.fna.fbcdn.net&_nc_cat=111&_nc_ohc=Inqvr8VuOMcAX-oYh0Y&edm=AABBvjUBAAAA&ccb=7-5&oh=00_AfC7Ky9pIOYSHLgCq3UgU-58Ujylk5IUrLlOB56nDDk7yA&oe=63C3F3E2&_nc_sid=83d603","https://instagram.fkhi22-1.fna.fbcdn.net/v/t51.2885-15/299167860_794108298427141_5190835097495348133_n.jpg?stp=dst-jpg_e35_p1080x1080&_nc_ht=instagram.fkhi22-1.fna.fbcdn.net&_nc_cat=101&_nc_ohc=o1TaG81YPz8AX9IZJYM&edm=AABBvjUBAAAA&ccb=7-5&oh=00_AfDW0i6W6koIq0t9fjhyajABKlk_sxGhKMdIilkGSzGL8A&oe=63C401B3&_nc_sid=83d603","https://instagram.fkhi22-1.fna.fbcdn.net/v/t51.2885-15/298811132_1675447386172959_335504285074247975_n.jpg?stp=dst-jpg_e35_p1080x1080&_nc_ht=instagram.fkhi22-1.fna.fbcdn.net&_nc_cat=103&_nc_ohc=nRVRxRGsA_cAX9AhTJi&edm=AABBvjUBAAAA&ccb=7-5&oh=00_AfCWwnJGUrkbShFFtIzg_ZFR0jgdhAKSa733_2_saHV0mA&oe=63C3964B&_nc_sid=83d603"],"location_slug":"","location_id":"","last_comment_ref":"18035362282383122","top_comments":[],"sentiment_distribution":{"neg":0,"pos":0,"neu":0},"positive_comments":[],"demos_failed":true,"id":null}},{"date":1661990400000,"post":{"tiktok_post_id":null,"url":"https://www.instagram.com/p/CiIjJghI0UB","post_user_id":"5a3daafaedc29549b4bc3bd1","channel":"instagram","author":"justinbieber","created_at":"2022-09-05T17:33:56","title":"LOVE YOU RIO 📷: @evanpaterakis","image_url":"https://s3-us-west-2.amazonaws.com/crawler.img/6317cd203fffda5521218e8f.jpg","avatar":"https://instagram.fbud6-4.fna.fbcdn.net/v/t51.2885-19/271177452_149300624107486_238439661515940835_n.jpg?stp=dst-jpg_s150x150&_nc_ht=instagram.fbud6-4.fna.fbcdn.net&_nc_cat=1&_nc_ohc=Yv2fHzN--kMAX_6-DjX&edm=AKEQFekBAAAA&ccb=7-5&oh=00_AfDXqRH-Ab9w_n80aFHsor4SfgMXKXnTEXnfK_f2cTKrGQ&oe=63F19E5F&_nc_sid=035b3a","content":null,"likes":4763116,"comments":95175,"is_business":true,"clean":true,"last_update_time":"2023-02-15T06:02:18.082619","followers":277140384,"max_price":1255031,"min_price":1252698,"location_name":"","location_public":false,"is_video":false,"album":["https://instagram.fjai2-4.fna.fbcdn.net/v/t51.2885-15/305053270_1244495332951690_1900272691137306634_n.jpg?stp=dst-jpg_e35_p1080x1080&_nc_ht=instagram.fjai2-4.fna.fbcdn.net&_nc_cat=110&_nc_ohc=RDpfMFg6nk0AX-mYnoc&edm=AABBvjUBAAAA&ccb=7-5&oh=00_AfCNdLf8WZvvkC-dBR0uzA0Mtu647vIWnxmn-l5_iO9hdg&oe=63F17770&_nc_sid=83d603","https://instagram.fjai2-3.fna.fbcdn.net/v/t51.2885-15/305655244_3964093137048277_8140427458049522485_n.jpg?stp=dst-jpg_e35_p1080x1080&_nc_ht=instagram.fjai2-3.fna.fbcdn.net&_nc_cat=101&_nc_ohc=scE9NfgRv7cAX-S_4pP&edm=AABBvjUBAAAA&ccb=7-5&oh=00_AfA17jrzROZcYZBibsSA74kWSf5L7pUbUHJvJ4xm94JizA&oe=63F1242C&_nc_sid=83d603","https://instagram.fjai2-2.fna.fbcdn.net/v/t51.2885-15/304866058_1132559654021612_7076891239380637548_n.jpg?stp=dst-jpg_e35_p1080x1080&_nc_ht=instagram.fjai2-2.fna.fbcdn.net&_nc_cat=108&_nc_ohc=wvXKGeD8JWMAX8422ao&edm=AABBvjUBAAAA&ccb=7-5&oh=00_AfBq6vpeLIbg9Frb4Z8TzF3DFhVxuyvXrP-hnn47Gm9geg&oe=63F0F2D3&_nc_sid=83d603","https://instagram.fjai2-3.fna.fbcdn.net/v/t51.2885-15/305066998_101536616019995_2057726823357319224_n.jpg?stp=dst-jpg_e35_p1080x1080&_nc_ht=instagram.fjai2-3.fna.fbcdn.net&_nc_cat=111&_nc_ohc=RU2O38qIK8UAX-20tf8&edm=AABBvjUBAAAA&ccb=7-5&oh=00_AfDAeyQKuy3BasYJ8xiGqiLwcwSv_GmXBu6wQ5OZdPls0Q&oe=63F1B7F2&_nc_sid=83d603","https://instagram.fjai2-2.fna.fbcdn.net/v/t51.2885-15/304918245_447659950640271_1835952251294837380_n.jpg?stp=dst-jpg_e35_p1080x1080&_nc_ht=instagram.fjai2-2.fna.fbcdn.net&_nc_cat=103&_nc_ohc=4BZ3VCB65GoAX9QMOLg&edm=AABBvjUBAAAA&ccb=7-5&oh=00_AfAqkH_ux_lFKtMxtTngs72CZVUkynr0bD0YNAmH9cb1Eg&oe=63F21624&_nc_sid=83d603","https://instagram.fjai2-4.fna.fbcdn.net/v/t51.2885-15/304861022_600646158273474_8648425227297301948_n.jpg?stp=dst-jpg_e35_p1080x1080&_nc_ht=instagram.fjai2-4.fna.fbcdn.net&_nc_cat=106&_nc_ohc=K8GbZz9NDgkAX8eYBPt&edm=AABBvjUBAAAA&ccb=7-5&oh=00_AfAiR9z3kuiA5gUW9bpPhwQWUNbw62q4wOq4pJNn3jl-CA&oe=63F10CCF&_nc_sid=83d603","https://instagram.fjai2-3.fna.fbcdn.net/v/t51.2885-15/304865221_616624869910236_655915208989982169_n.jpg?stp=dst-jpg_e35_p1080x1080&_nc_ht=instagram.fjai2-3.fna.fbcdn.net&_nc_cat=100&_nc_ohc=ovBM8sKbLAYAX_4eJcd&edm=AABBvjUBAAAA&ccb=7-5&oh=00_AfB5fU0P2VMUfbkzPLuKGiW-wLJLj1E9zaTyRiGx_hv-yA&oe=63F0D032&_nc_sid=83d603","https://instagram.fjai2-3.fna.fbcdn.net/v/t51.2885-15/304860874_1060076501379311_5400892969970728585_n.jpg?stp=dst-jpg_e35_p1080x1080&_nc_ht=instagram.fjai2-3.fna.fbcdn.net&_nc_cat=111&_nc_ohc=TWxkGV2RPIQAX80KDvm&edm=AABBvjUBAAAA&ccb=7-5&oh=00_AfC5DtuhXbQgaTSMLSZqoZ8TM73DkVJOZdesEifB99iQJQ&oe=63F17493&_nc_sid=83d603"],"location_slug":"","location_id":"","last_comment_ref":"18228761068159665","brand_mentions":[],"embedded_links":[],"top_comments":[],"sentiment_distribution":{"neg":0,"pos":0,"neu":0},"positive_comments":[],"demos_failed":true,"id":null}},{"date":1664582400000,"post":{"tiktok_post_id":null,"url":"https://www.instagram.com/p/CkZRRMQvwfQ","post_user_id":"5a3daafaedc29549b4bc3bd1","channel":"instagram","author":"justinbieber","created_at":"2022-10-31T22:27:34","title":"Happy Halloween 🎃 📸 @amberasaly","image_url":"https://s3-us-west-2.amazonaws.com/crawler.img/636212d6665a7b1b1402ebc5.jpg","avatar":"https://scontent-sea1-1.xx.fbcdn.net/v/t51.2885-15/350507605_1017436996365336_5254999826464604062_n.jpg?_nc_cat=1&ccb=1-7&_nc_sid=86c713&_nc_ohc=_VsNMdM_EvUAX92ST2b&_nc_ht=scontent-sea1-1.xx&edm=AL-3X8kEAAAA&oh=00_AfBqYaZwRv6rk0OTukTndzfY5dEprc6uz6b3YemLd5GZ3g&oe=64D0F68C","content":null,"likes":4047930,"comments":28473,"is_business":true,"clean":true,"brand_mentions":[],"embedded_links":[],"last_update_time":"2023-08-03T11:39:07.862442","followers":293314634,"max_price":1328871,"min_price":1326761,"location_name":"","location_public":false,"is_video":false,"album":["https://instagram.fblr4-5.fna.fbcdn.net/v/t51.2885-15/313374187_537684051523043_1282252261340873370_n.jpg?stp=dst-jpg_e35_p1080x1080&_nc_ht=instagram.fblr4-5.fna.fbcdn.net&_nc_cat=111&_nc_ohc=gJSdEKD3JQQAX_28EfB&edm=AABBvjUBAAAA&ccb=7-5&oh=00_AfCD0W3Lx1OgLoRCzf6vr-iO6pXEwaVv3HFMP-O-5HM1Fg&oe=64D0951F&_nc_sid=4f4799","https://instagram.fblr4-4.fna.fbcdn.net/v/t51.2885-15/313287747_118374614231430_3922132166845547276_n.jpg?stp=dst-jpg_e35_p1080x1080&_nc_ht=instagram.fblr4-4.fna.fbcdn.net&_nc_cat=106&_nc_ohc=NJ1tgXi_QiYAX-dfZrs&edm=AABBvjUBAAAA&ccb=7-5&oh=00_AfB5flewG0dJlUkThSWbG6kTs7ZMzac3QdwbkkWhO6oYmQ&oe=64CFE4A6&_nc_sid=4f4799","https://instagram.fblr4-1.fna.fbcdn.net/v/t51.2885-15/313346829_120878920634337_2630429762419917910_n.jpg?stp=dst-jpg_e35_p1080x1080&_nc_ht=instagram.fblr4-1.fna.fbcdn.net&_nc_cat=109&_nc_ohc=aFct5ApUz3oAX9wIF88&edm=AABBvjUBAAAA&ccb=7-5&oh=00_AfAH5sZFMg9e8jiX0JAP9aAVaAPs4HCLS1983a9UctNCFA&oe=64D0910E&_nc_sid=4f4799","https://instagram.fblr4-5.fna.fbcdn.net/v/t51.2885-15/313348579_887064929338919_6690107469352184846_n.jpg?stp=dst-jpg_e35_p1080x1080&_nc_ht=instagram.fblr4-5.fna.fbcdn.net&_nc_cat=111&_nc_ohc=lDsOlTquO-QAX_PzW4b&edm=AABBvjUBAAAA&ccb=7-5&oh=00_AfAUQrnMulCv5mpZz1PJurrHcQSQlVTHppKD6_mSYKJoyA&oe=64D071B9&_nc_sid=4f4799","https://instagram.fblr4-2.fna.fbcdn.net/v/t51.2885-15/313343990_679449250429997_2043984547403895928_n.jpg?stp=dst-jpg_e35_p1080x1080&_nc_ht=instagram.fblr4-2.fna.fbcdn.net&_nc_cat=105&_nc_ohc=VrOlM-fksqYAX8wjxeF&edm=AABBvjUBAAAA&ccb=7-5&oh=00_AfD5EawkHPIof0_C1HxklYsv1oj739azyrHOt1Zv-1gBPQ&oe=64D0E809&_nc_sid=4f4799","https://instagram.fblr4-3.fna.fbcdn.net/v/t51.2885-15/313810790_3422467191357000_9102746217466803204_n.jpg?stp=dst-jpg_e35_p1080x1080&_nc_ht=instagram.fblr4-3.fna.fbcdn.net&_nc_cat=100&_nc_ohc=WpBZ1RCHU8wAX8JLYK6&edm=AABBvjUBAAAA&ccb=7-5&oh=00_AfDWbHYQ86hYigSnKsF--yNn5ACIs2pOlZ6xco-uBp9Ixw&oe=64CFDB46&_nc_sid=4f4799"],"location_slug":"","location_id":"","top_comments":[],"sentiment_distribution":{"neg":0,"pos":0,"neu":0},"positive_comments":[],"demos_failed":true,"id":null,"is_album":true,"album_video":["","","","","",""]}},{"date":1667260800000,"post":{"tiktok_post_id":null,"url":"https://www.instagram.com/p/ClPo-j8J18q","post_user_id":"5a3daafaedc29549b4bc3bd1","channel":"instagram","author":"justinbieber","created_at":"2022-11-22T01:13:44+00:00","title":"HAPPY BIRFDAY (in Japan) TO MY FAVORITE HUMAN BEING XOXO YOU MAKE LIFE MAGIC 😭 OBSESSED WITH EVERYTHING ABOUT YOU. LOVE YOU BUM BUM","image_url":"https://scontent-sea1-1.cdninstagram.com/v/t51.29350-15/316350820_129712489699005_706615911239265401_n.jpg?_nc_cat=110&ccb=1-7&_nc_sid=18de74&_nc_ohc=J0b0rAmemjUAX9TMQuZ&_nc_ht=scontent-sea1-1.cdninstagram.com&edm=AL-3X8kEAAAA&oh=00_AfDUgZlKJCYHuAtAyZqqoZ-5sDYxcu6sumzNKZ-O5Eo0cg&oe=660ACC8B","avatar":"https://scontent-sea1-1.xx.fbcdn.net/v/t51.2885-15/350507605_1017436996365336_5254999826464604062_n.jpg?_nc_cat=1&ccb=1-7&_nc_sid=7d201b&_nc_ohc=BmjUBhscKkcAX-z1f6d&_nc_ht=scontent-sea1-1.xx&edm=AL-3X8kEAAAA&oh=00_AfDM9ICu4UEvBwN7lZfxaOFs6FrzPZt6dFO_ynUJex1P7w&oe=660B644C","content":null,"likes":7898298,"comments":33250,"is_business":true,"clean":true,"last_update_time":"2023-11-11T16:30:07.340193","followers":292814520,"max_price":1326067,"min_price":1323949,"location_name":"","location_public":false,"is_video":false,"album":["https://instagram.fmga3-2.fna.fbcdn.net/v/t51.2885-15/316350820_129712489699005_706615911239265401_n.jpg?stp=dst-jpg_e35_s1080x1080&_nc_ht=instagram.fmga3-2.fna.fbcdn.net&_nc_cat=109&_nc_ohc=0XsBIGPUm5QAX_GhKRJ&edm=AABBvjUBAAAA&ccb=7-5&oh=00_AfBcqdfT8iPbb2hKDFKaxlKDtj10-eozqLBguyLWwcFbqA&oe=655565FA&_nc_sid=4f4799","https://instagram.fmga3-1.fna.fbcdn.net/v/t51.2885-15/316178727_8685701771441704_7089907997773936937_n.jpg?stp=dst-jpg_e35_s1080x1080&_nc_ht=instagram.fmga3-1.fna.fbcdn.net&_nc_cat=104&_nc_ohc=91EHWRrbiOwAX_Kj9ol&edm=AABBvjUBAAAA&ccb=7-5&oh=00_AfB7UYBzOQWpRuld5MIVta7xbhm33mtKbBllnbgR07WmWQ&oe=655537CD&_nc_sid=4f4799","https://instagram.fmga3-1.fna.fbcdn.net/v/t51.2885-15/316478898_444699954301002_3568667446306818268_n.jpg?stp=dst-jpg_e35_s1080x1080&_nc_ht=instagram.fmga3-1.fna.fbcdn.net&_nc_cat=106&_nc_ohc=Fimx7r6x6WMAX_P3kvP&edm=AABBvjUBAAAA&ccb=7-5&oh=00_AfCNPSdX3pSwXIYhV2zeBSwS2BZsV0UujmvbDkNNXPG5DQ&oe=65547906&_nc_sid=4f4799","https://instagram.fmga3-2.fna.fbcdn.net/v/t51.2885-15/316321765_692324965580601_2881127190374957895_n.jpg?stp=dst-jpg_e35_s1080x1080&_nc_ht=instagram.fmga3-2.fna.fbcdn.net&_nc_cat=109&_nc_ohc=t2OEEHMImxIAX9pozOs&edm=AABBvjUBAAAA&ccb=7-5&oh=00_AfCX_3ZpQFn26_map_TqQfHa_J6vGC0fCPoMlc6mtdS4Kw&oe=6554D8C3&_nc_sid=4f4799","https://instagram.fmga3-1.fna.fbcdn.net/v/t51.2885-15/316480579_153544244082913_4610130275575948804_n.jpg?stp=dst-jpg_e35_s1080x1080&_nc_ht=instagram.fmga3-1.fna.fbcdn.net&_nc_cat=101&_nc_ohc=rLBh_Sm3ovgAX8JtxPJ&edm=AABBvjUBAAAA&ccb=7-5&oh=00_AfB7k_tbQQZsnuPUoMDpfzd9c_IlfqLuvSySSojunaSlDQ&oe=6553EC29&_nc_sid=4f4799","https://instagram.fmga3-2.fna.fbcdn.net/v/t51.2885-15/316217791_1316458332442694_7590968449319328595_n.jpg?stp=dst-jpg_e35_s1080x1080&_nc_ht=instagram.fmga3-2.fna.fbcdn.net&_nc_cat=102&_nc_ohc=Bll_ejTfIBgAX8Pv4G7&edm=AABBvjUBAAAA&ccb=7-5&oh=00_AfB8CoIgISunPEfW2akllK5VAqLf3EnO3lVnNJ2j5sEGrg&oe=65552609&_nc_sid=4f4799"],"location_slug":"","location_id":"","brand_mentions":[{"name":"About you","logo":"https://superboostaa.s3.us-west-2.amazonaws.com/about-you_1626246344165.jpg","key":"about-you"}],"embedded_links":[],"top_comments":[],"sentiment_distribution":{"neg":0,"pos":0,"neu":0},"positive_comments":[],"demos_failed":true,"id":null,"album_video":["","","","","",""],"is_album":true}},{"date":1669852800000,"post":{"tiktok_post_id":null,"url":"https://www.instagram.com/p/Clo2zogSFfd","post_user_id":"5a3daafaedc29549b4bc3bd1","channel":"instagram","author":"justinbieber","created_at":"2022-12-01T20:15:35+00:00","title":"Thinkin of renting a van and going radio station to radio station like the good ol days ryangood24 djtayjames pattiemallette LOVE YOU GUYS","image_url":"https://scontent-sea1-1.cdninstagram.com/v/t51.29350-15/317480946_229063062779379_8276531634619077358_n.jpg?_nc_cat=1&ccb=1-7&_nc_sid=8ae9d6&_nc_ohc=gO3PSJPc2vAAX_aBEYM&_nc_ht=scontent-sea1-1.cdninstagram.com&edm=AL-3X8kEAAAA&oh=00_AfCb4ZFC4GFnCdfey8RorAuY15MXpszvdyvR7GR2XwSc5A&oe=63C05C1A","avatar":"https://scontent-sea1-1.xx.fbcdn.net/v/t51.2885-15/271177452_149300624107486_238439661515940835_n.jpg?_nc_cat=1&ccb=1-7&_nc_sid=86c713&_nc_ohc=y9kRq_inJdMAX9Zsbek&_nc_ht=scontent-sea1-1.xx&edm=AL-3X8kEAAAA&oh=00_AfBgqcSwlUFTxiErOd_Jp_wC6J-mQDcKsKQmr79GeV1LJQ&oe=63C15442","content":null,"likes":1700870,"comments":20078,"is_business":true,"clean":true,"last_update_time":"2023-01-09T01:18:16.337851","followers":272742310,"max_price":2546112,"min_price":1505677,"location_name":"","location_public":false,"is_video":false,"album":[],"location_slug":"","location_id":"","brand_mentions":[],"embedded_links":[],"top_comments":[],"sentiment_distribution":{"neg":0,"pos":0,"neu":0},"positive_comments":[],"demos_failed":true,"deleted":true,"inactive":true}},{"date":1672531200000,"post":{"tiktok_post_id":null,"url":"https://www.instagram.com/p/Cnc_o-9vDjt","post_user_id":"5a3daafaedc29549b4bc3bd1","channel":"instagram","author":"justinbieber","created_at":"2023-01-15T22:44:40+00:00","title":"obb","image_url":"https://scontent-sea1-1.cdninstagram.com/v/t51.29350-15/325440701_749356406175091_8051181906694906731_n.jpg?_nc_cat=104&ccb=1-7&_nc_sid=18de74&_nc_ohc=i4vedgvsvJwAX8Qb9Nk&_nc_ht=scontent-sea1-1.cdninstagram.com&edm=AL-3X8kEAAAA&oh=00_AfAj-LGdmNstYnaiiwFohjuGdy7S75dKvA8ruAiJdQgCkw&oe=660B4C57","avatar":"https://scontent-sea1-1.xx.fbcdn.net/v/t51.2885-15/350507605_1017436996365336_5254999826464604062_n.jpg?_nc_cat=1&ccb=1-7&_nc_sid=7d201b&_nc_ohc=BmjUBhscKkcAX-z1f6d&_nc_ht=scontent-sea1-1.xx&edm=AL-3X8kEAAAA&oh=00_AfDM9ICu4UEvBwN7lZfxaOFs6FrzPZt6dFO_ynUJex1P7w&oe=660B644C","content":null,"likes":3544717,"comments":17331,"is_business":true,"clean":true,"brand_mentions":[],"embedded_links":[],"last_update_time":"2024-01-13T02:52:28.156450","followers":292028570,"max_price":1326758,"min_price":1324642,"location_name":"","location_public":false,"is_video":false,"album":["https://instagram.fman2-2.fna.fbcdn.net/v/t51.2885-15/325440701_749356406175091_8051181906694906731_n.jpg?stp=dst-jpg_e35_p1080x1080&_nc_ht=instagram.fman2-2.fna.fbcdn.net&_nc_cat=107&_nc_ohc=w0XhEKxyTRYAX_XrSua&edm=AABBvjUBAAAA&ccb=7-5&oh=00_AfCb-AEApw9Uy_BCLhyLUhC3tyCfjlKLXWTE7iT2O9Eb0Q&oe=65A72B11&_nc_sid=4f4799","https://instagram.fman2-2.fna.fbcdn.net/v/t51.2885-15/325438739_192769776761200_8583579754004946089_n.jpg?stp=dst-jpg_e35_p1080x1080&_nc_ht=instagram.fman2-2.fna.fbcdn.net&_nc_cat=104&_nc_ohc=6_eov2YqZ9UAX_LC4x9&edm=AABBvjUBAAAA&ccb=7-5&oh=00_AfD3VTzERmbzETO5nvap17kXaU13yBcGeRnsDynslhoiSQ&oe=65A69EB3&_nc_sid=4f4799","https://instagram.fman2-1.fna.fbcdn.net/v/t51.2885-15/325817071_481925917445174_452861707548906926_n.jpg?stp=dst-jpg_e35_p1080x1080&efg=e30&_nc_ht=instagram.fman2-1.fna.fbcdn.net&_nc_cat=102&_nc_ohc=GnDWgyaneMkAX96Sp9c&edm=AABBvjUBAAAA&ccb=7-5&oh=00_AfBhvP7k912WaYT8Rxi2v6xshjm0yzqHTIALUUhm84QhZg&oe=65A6929E&_nc_sid=4f4799","https://instagram.fman2-1.fna.fbcdn.net/v/t51.2885-15/325510466_2732902810178041_3693639709634959179_n.jpg?stp=dst-jpg_e35_p1080x1080&_nc_ht=instagram.fman2-1.fna.fbcdn.net&_nc_cat=101&_nc_ohc=p6CzkLpju3IAX9NROy2&edm=AABBvjUBAAAA&ccb=7-5&oh=00_AfBIHXVRVCkXd1g1WM0H25YVrgNROhOUijc-HxQMXKaOhg&oe=65A646C2&_nc_sid=4f4799","https://instagram.fman2-1.fna.fbcdn.net/v/t51.2885-15/325473128_566116435107920_333022710497456492_n.jpg?stp=dst-jpg_e35_p1080x1080&_nc_ht=instagram.fman2-1.fna.fbcdn.net&_nc_cat=108&_nc_ohc=7a5ZtIWYBesAX-W-yzq&edm=AABBvjUBAAAA&ccb=7-5&oh=00_AfDkXIc6KtLa8jOvzt-sg6SF6jr9ErT2qkFJ9r8xIl_GAQ&oe=65A63E80&_nc_sid=4f4799"],"location_slug":"","location_id":"","top_comments":[],"sentiment_distribution":{"neg":0,"pos":0,"neu":0},"positive_comments":[],"id":null,"demos_failed":true,"album_video":["","","","",""],"is_album":true}},{"date":1675209600000,"post":{"tiktok_post_id":null,"url":"https://www.instagram.com/p/CoYAMeMyM_g","post_user_id":"5a3daafaedc29549b4bc3bd1","channel":"instagram","author":"justinbieber","created_at":"2023-02-07T20:44:43+00:00","title":"❤️🌈🥰","image_url":"https://scontent-sea1-1.cdninstagram.com/v/t51.29350-15/329249480_1270230816865041_5050468282718246541_n.jpg?_nc_cat=102&ccb=1-7&_nc_sid=18de74&_nc_ohc=qjZuT6ODqpUAX8P9SJW&_nc_ht=scontent-sea1-1.cdninstagram.com&edm=AL-3X8kEAAAA&oh=00_AfBDBPD-znblLO0SIKVcqb3gzdWrW_MgK5T1QTSODizN9g&oe=660B37B6","avatar":"https://scontent-sea1-1.xx.fbcdn.net/v/t51.2885-15/350507605_1017436996365336_5254999826464604062_n.jpg?_nc_cat=1&ccb=1-7&_nc_sid=7d201b&_nc_ohc=BmjUBhscKkcAX-z1f6d&_nc_ht=scontent-sea1-1.xx&edm=AL-3X8kEAAAA&oh=00_AfDM9ICu4UEvBwN7lZfxaOFs6FrzPZt6dFO_ynUJex1P7w&oe=660B644C","content":null,"likes":7898856,"comments":37792,"is_business":true,"clean":true,"last_update_time":"2024-01-13T02:51:54.521374","followers":292028570,"max_price":1326758,"min_price":1324642,"location_name":"","location_public":false,"is_video":false,"album":["https://instagram.fsal1-1.fna.fbcdn.net/v/t51.2885-15/329249480_1270230816865041_5050468282718246541_n.jpg?stp=dst-jpg_e35_p1080x1080&_nc_ht=instagram.fsal1-1.fna.fbcdn.net&_nc_cat=109&_nc_ohc=IAldaPsy-WYAX_3WG-h&edm=AABBvjUBAAAA&ccb=7-5&oh=00_AfAJ2KTp3JPIRynIoEzWsZ0kGK_Pout1_VXo_A2LjZ_iZA&oe=65A70A97&_nc_sid=4f4799","https://instagram.fsal1-1.fna.fbcdn.net/v/t51.2885-15/329226244_755378015946587_3262858656956895183_n.jpg?stp=dst-jpg_e35_p1080x1080&_nc_ht=instagram.fsal1-1.fna.fbcdn.net&_nc_cat=111&_nc_ohc=4gU8MiK4cOcAX887W4i&edm=AABBvjUBAAAA&ccb=7-5&oh=00_AfCG9XI4oUjCLGk24p6gUzc3MScZ33peG78VWb6gslXquA&oe=65A72745&_nc_sid=4f4799","https://instagram.fsal1-1.fna.fbcdn.net/v/t51.2885-15/329854934_6271826332828897_1032413384558853355_n.jpg?stp=dst-jpg_e35_p1080x1080&_nc_ht=instagram.fsal1-1.fna.fbcdn.net&_nc_cat=101&_nc_ohc=wDu0jgyBFgoAX95tnWD&edm=AABBvjUBAAAA&ccb=7-5&oh=00_AfDX11D4FohQ6AxdExAamHYA91qOYMaMhUA5c-Qs96fiRQ&oe=65A7BF21&_nc_sid=4f4799","https://instagram.fsal1-1.fna.fbcdn.net/v/t51.2885-15/329751143_135828209378037_4310823549995722836_n.jpg?stp=dst-jpg_e35_p1080x1080&_nc_ht=instagram.fsal1-1.fna.fbcdn.net&_nc_cat=109&_nc_ohc=gl-6MW6xX-AAX8IJbAM&edm=AABBvjUBAAAA&ccb=7-5&oh=00_AfCVon1-74dmP_Je9ATrBLf0A3jLUIzRxVo-qzmviu8AfA&oe=65A6A751&_nc_sid=4f4799","https://instagram.fsal1-1.fna.fbcdn.net/v/t51.2885-15/328975104_907364843728331_1542689638271441761_n.jpg?stp=dst-jpg_e35_p1080x1080&_nc_ht=instagram.fsal1-1.fna.fbcdn.net&_nc_cat=111&_nc_ohc=-yGmRdbmKfYAX9FFTtz&edm=AABBvjUBAAAA&ccb=7-5&oh=00_AfDx4XHC2hPoG50eBijinX0vkDAW1hbLR_Lz00-LVZ_orA&oe=65A7BA81&_nc_sid=4f4799","https://instagram.fsal1-1.fna.fbcdn.net/v/t51.2885-15/329687370_6126876877334507_3161115349961574984_n.jpg?stp=dst-jpg_e35_p1080x1080&_nc_ht=instagram.fsal1-1.fna.fbcdn.net&_nc_cat=111&_nc_ohc=teygO3AGBT8AX8Kq0bo&edm=AABBvjUBAAAA&ccb=7-5&oh=00_AfARnzw6BEv8Amc3-VrRNgS3PZdOMHoZ1oZ0evWky1szTg&oe=65A67F4D&_nc_sid=4f4799","https://instagram.fsal1-1.fna.fbcdn.net/v/t51.2885-15/329236252_232785389107039_7895671246127909817_n.jpg?stp=dst-jpg_e35_p1080x1080&_nc_ht=instagram.fsal1-1.fna.fbcdn.net&_nc_cat=107&_nc_ohc=VXTLlN0rou4AX83b0Lt&edm=AABBvjUBAAAA&ccb=7-5&oh=00_AfC7ETnOQ5YamJ5E_9CMpG2GbOgqjpghPJ7WEpat4IqyWQ&oe=65A7C171&_nc_sid=4f4799"],"location_slug":"","location_id":"","brand_mentions":[],"embedded_links":[],"top_comments":[],"sentiment_distribution":{"neg":0,"pos":0,"neu":0},"positive_comments":[],"id":null,"demos_failed":true,"album_video":["","","","","","",""],"is_album":true}},{"date":1677628800000,"post":{"tiktok_post_id":null,"url":"https://www.instagram.com/p/CpsfJ0qOdSL","post_user_id":"5a3daafaedc29549b4bc3bd1","channel":"instagram","author":"justinbieber","created_at":"2023-03-12T16:11:26+00:00","title":"LUV U BABY","image_url":"https://scontent-sea1-1.cdninstagram.com/v/t51.29350-15/334700610_1224742935089672_7426417767505950062_n.jpg?_nc_cat=105&ccb=1-7&_nc_sid=18de74&_nc_ohc=lHTShS5WL4sAX9v_A74&_nc_ht=scontent-sea1-1.cdninstagram.com&edm=AL-3X8kEAAAA&oh=00_AfAM-cz8ehVdHs48FG5ubjj74gCUBICaxJhtYZSwvBjyRQ&oe=660AE02F","avatar":"https://scontent-sea1-1.xx.fbcdn.net/v/t51.2885-15/350507605_1017436996365336_5254999826464604062_n.jpg?_nc_cat=1&ccb=1-7&_nc_sid=7d201b&_nc_ohc=BmjUBhscKkcAX-z1f6d&_nc_ht=scontent-sea1-1.xx&edm=AL-3X8kEAAAA&oh=00_AfDM9ICu4UEvBwN7lZfxaOFs6FrzPZt6dFO_ynUJex1P7w&oe=660B644C","content":null,"likes":8618177,"comments":104828,"is_business":true,"clean":true,"brand_mentions":[],"embedded_links":[],"last_update_time":"2024-01-13T02:48:32.330024","followers":292028570,"max_price":1326758,"min_price":1324642,"location_name":"","location_public":false,"is_video":false,"album":["https://instagram.fpos2-1.fna.fbcdn.net/v/t51.2885-15/334700610_1224742935089672_7426417767505950062_n.jpg?stp=dst-jpg_e35_p1080x1080&_nc_ht=instagram.fpos2-1.fna.fbcdn.net&_nc_cat=108&_nc_ohc=qDQ6scABfQsAX9ljYC5&edm=AABBvjUBAAAA&ccb=7-5&oh=00_AfCqaepfGzECl2eZ_t9QBdqP_5Ty5PwzBPMTX3Wgu_zv7g&oe=65A7D74E&_nc_sid=4f4799","https://instagram.fpos2-1.fna.fbcdn.net/v/t51.2885-15/334601077_608038854094800_6817772854755985628_n.jpg?stp=dst-jpg_e35_p1080x1080&_nc_ht=instagram.fpos2-1.fna.fbcdn.net&_nc_cat=100&_nc_ohc=uRgcZcKK_Y8AX_rSQh5&edm=AABBvjUBAAAA&ccb=7-5&oh=00_AfDPZiJjh9m13LdqGEdc2rXLBX5GqsomOMVOF4WW3Cd7wA&oe=65A787BD&_nc_sid=4f4799"],"location_slug":"","location_id":"","top_comments":[],"sentiment_distribution":{"neg":0,"pos":0,"neu":0},"positive_comments":[],"demos_failed":true,"album_video":["",""],"is_album":true,"id":null}},{"date":1680307200000,"post":{"tiktok_post_id":null,"url":"https://www.instagram.com/p/CrKdym9uQt8","post_user_id":"5a3daafaedc29549b4bc3bd1","channel":"instagram","author":"justinbieber","created_at":"2023-04-18T04:08:08+00:00","title":"I was blown away by Frank Oceans Coachella performance. His artistry is simply unmatched, his style, his taste, his voice, his attention to detail.. I was deeply moved. It made me want to keep going  and get better as an artist. He continues to set the bar high and gave me a night I will never forget! Thanks Frank.","image_url":"https://scontent-sea1-1.cdninstagram.com/v/t51.29350-15/341548897_2404536056385003_2072663802457509581_n.jpg?_nc_cat=108&ccb=1-7&_nc_sid=18de74&_nc_ohc=-jTWGkpHemgAX9ZbpVf&_nc_ht=scontent-sea1-1.cdninstagram.com&edm=AL-3X8kEAAAA&oh=00_AfBnxNvCOe0bQd5Ol6h7-N-ojogYq6g_QBzJAEx_8pUVGg&oe=660B499B","avatar":"https://scontent-sea1-1.xx.fbcdn.net/v/t51.2885-15/350507605_1017436996365336_5254999826464604062_n.jpg?_nc_cat=1&ccb=1-7&_nc_sid=7d201b&_nc_ohc=BmjUBhscKkcAX-z1f6d&_nc_ht=scontent-sea1-1.xx&edm=AL-3X8kEAAAA&oh=00_AfDM9ICu4UEvBwN7lZfxaOFs6FrzPZt6dFO_ynUJex1P7w&oe=660B644C","content":null,"likes":1555854,"comments":22,"is_business":true,"clean":true,"last_update_time":"2024-02-03T11:06:01.037560","followers":292962550,"max_price":1326937,"min_price":1324821,"location_name":"","location_public":false,"is_video":false,"album":[],"album_video":[],"location_slug":"","location_id":"","brand_mentions":[{"name":"Coachella","logo":"https://superboostaa.s3.us-west-2.amazonaws.com/coachella_1626243315715.jpg","key":"coachella"},{"name":"Artistry","logo":"https://superboostaa.s3.us-west-2.amazonaws.com/artistry_1626245559637.jpg","key":"artistry"}],"embedded_links":[],"top_comments":[],"sentiment_distribution":{"neg":0,"pos":0,"neu":0},"positive_comments":[],"demos_failed":true,"video_url":null,"id":null}},{"date":1682899200000,"post":{"tiktok_post_id":null,"url":"https://www.instagram.com/p/CsZF3vQuwZu","post_user_id":"5a3daafaedc29549b4bc3bd1","channel":"instagram","author":"justinbieber","created_at":"2023-05-18T16:59:08+00:00","title":"Proud of you 🥹 rhode launching in UK 🫣🫣","image_url":"https://scontent-sea1-1.cdninstagram.com/v/t51.29350-15/347468440_2539536782867383_6807985310829862633_n.jpg?_nc_cat=101&ccb=1-7&_nc_sid=18de74&_nc_ohc=ueIYVRAoE-YAX_qM0vy&_nc_ht=scontent-sea1-1.cdninstagram.com&edm=AL-3X8kEAAAA&oh=00_AfCERa6tYLEbS3ukMVl1fz1-oZ9W4OJ3G2b_3U-lhWRm4Q&oe=660ACA29","avatar":"https://scontent-sea1-1.xx.fbcdn.net/v/t51.2885-15/350507605_1017436996365336_5254999826464604062_n.jpg?_nc_cat=1&ccb=1-7&_nc_sid=7d201b&_nc_ohc=BmjUBhscKkcAX-z1f6d&_nc_ht=scontent-sea1-1.xx&edm=AL-3X8kEAAAA&oh=00_AfDM9ICu4UEvBwN7lZfxaOFs6FrzPZt6dFO_ynUJex1P7w&oe=660B644C","content":null,"is_album":true,"likes":5482547,"comments":68164,"is_business":true,"album_video":["","",""],"album":["https://scontent-atl3-1.cdninstagram.com/v/t51.2885-15/347468440_2539536782867383_6807985310829862633_n.jpg?stp=dst-jpg_e35_p1080x1080&_nc_ht=scontent-atl3-1.cdninstagram.com&_nc_cat=107&_nc_ohc=_7xgluJGb88AX887akD&edm=AABBvjUBAAAA&ccb=7-5&oh=00_AfBlaTpSJN3okpP4YRDTCwLbd17rKRDqZQyCCt62lTRYcw&oe=65C37ECC&_nc_sid=4f4799","https://scontent-atl3-2.cdninstagram.com/v/t51.2885-15/347541753_544369651242947_4975657690575293638_n.jpg?stp=dst-jpg_e35_p1080x1080&_nc_ht=scontent-atl3-2.cdninstagram.com&_nc_cat=111&_nc_ohc=jeTDt_EJNVgAX_qp-YE&edm=AABBvjUBAAAA&ccb=7-5&oh=00_AfCgamMfjkrdvRUwToy_sjN3_623wOeh0ojqm8xDmyoLrw&oe=65C3145A&_nc_sid=4f4799","https://scontent-atl3-1.cdninstagram.com/v/t51.2885-15/347403503_254646423785607_4805550512898616818_n.jpg?stp=dst-jpg_e35_p1080x1080&_nc_ht=scontent-atl3-1.cdninstagram.com&_nc_cat=103&_nc_ohc=d7CV2s1nZa0AX_Pznz8&edm=AABBvjUBAAAA&ccb=7-5&oh=00_AfAJ9zKp_cGBDwgmVWB-oxRtfBhOclatYDEZit-gR3OqJw&oe=65C259C1&_nc_sid=4f4799"],"clean":true,"last_update_time":"2024-02-03T11:05:50.872791","followers":292962550,"max_price":1326937,"min_price":1324821,"location_name":"","location_public":false,"is_video":false,"location_slug":"","location_id":"","brand_mentions":[],"embedded_links":[],"top_comments":[],"sentiment_distribution":{"neg":0,"pos":0,"neu":0},"positive_comments":[],"demos_failed":true,"video_url":null,"id":null,"deleted":true,"inactive":true}},{"date":1690848000000,"post":{"tiktok_post_id":null,"url":"https://www.instagram.com/p/Cwi9tUvxGGy","post_user_id":"5a3daafaedc29549b4bc3bd1","channel":"instagram","author":"justinbieber","created_at":"2023-08-29T23:05:47+00:00","title":"","image_url":"https://scontent-sea1-1.cdninstagram.com/v/t51.29350-15/371741558_1001570377848745_5413792966037651008_n.jpg?_nc_cat=101&ccb=1-7&_nc_sid=18de74&_nc_ohc=Vt6t-zjKcSEAX_29bB9&_nc_ht=scontent-sea1-1.cdninstagram.com&edm=AL-3X8kEAAAA&oh=00_AfAJH0nr2TnhMDrTCfIG9ogLZOgsLc-cc840Ywi_n9-EUg&oe=660ADDEC","avatar":"https://scontent-sea1-1.xx.fbcdn.net/v/t51.2885-15/350507605_1017436996365336_5254999826464604062_n.jpg?_nc_cat=1&ccb=1-7&_nc_sid=7d201b&_nc_ohc=BmjUBhscKkcAX-z1f6d&_nc_ht=scontent-sea1-1.xx&edm=AL-3X8kEAAAA&oh=00_AfDM9ICu4UEvBwN7lZfxaOFs6FrzPZt6dFO_ynUJex1P7w&oe=660B644C","content":null,"likes":5818031,"comments":37292,"is_business":true,"clean":true,"brand_mentions":[],"embedded_links":[],"last_update_time":"2024-02-03T11:04:44.534051","followers":292962550,"max_price":1326937,"min_price":1324821,"location_name":"","location_public":false,"is_video":false,"album":["https://instagram.fblr2-3.fna.fbcdn.net/v/t51.2885-15/371741558_1001570377848745_5413792966037651008_n.jpg?stp=dst-jpg_e35_p1080x1080&_nc_ht=instagram.fblr2-3.fna.fbcdn.net&_nc_cat=101&_nc_ohc=pF6-UR_61TkAX-R2P9h&edm=AABBvjUBAAAA&ccb=7-5&oh=00_AfCFV9ALb1Lv9eFLQKzymqLbYMIiCRWo8RQw8RN2dpsgZw&oe=65C26609&_nc_sid=4f4799","https://instagram.fblr2-3.fna.fbcdn.net/v/t51.2885-15/372754252_329539662849460_4006708950214669997_n.jpg?stp=dst-jpg_e35_p1080x1080&_nc_ht=instagram.fblr2-3.fna.fbcdn.net&_nc_cat=104&_nc_ohc=fr0pTomg2MQAX_BVmXO&edm=AABBvjUBAAAA&ccb=7-5&oh=00_AfAwyiYhg5fDbqHPbCol5lGeLzNUapRg6maq9JWER3suHw&oe=65C3F8B9&_nc_sid=4f4799","https://instagram.fblr2-3.fna.fbcdn.net/v/t51.2885-15/371363658_6462901163763072_9131127456839781106_n.jpg?stp=dst-jpg_e35_p1080x1080&_nc_ht=instagram.fblr2-3.fna.fbcdn.net&_nc_cat=100&_nc_ohc=ggZdXwOBQbcAX_2ntqw&edm=AABBvjUBAAAA&ccb=7-5&oh=00_AfDYLXjpU0PpwTccF-T8uO6_Yce3g-3KYap9oth4mYOU6Q&oe=65C377C9&_nc_sid=4f4799","https://instagram.fblr2-3.fna.fbcdn.net/v/t51.2885-15/372505775_634982965370676_7346429412442803428_n.jpg?stp=dst-jpg_e35_p1080x1080&_nc_ht=instagram.fblr2-3.fna.fbcdn.net&_nc_cat=100&_nc_ohc=ECj7X5Yc-68AX8Vsj8o&edm=AABBvjUBAAAA&ccb=7-5&oh=00_AfB0kM4M5iDxIelb6KGbvrAnv7lfpOg-Aqels65O1GhrGA&oe=65C2604F&_nc_sid=4f4799"],"album_video":["","","",""],"location_slug":"","location_id":"","top_comments":[],"sentiment_distribution":{"neg":0,"pos":0,"neu":0},"positive_comments":[],"demos_failed":true,"is_album":true,"id":null}},{"date":1693526400000,"post":{"tiktok_post_id":null,"url":"https://www.instagram.com/p/CxJw8_ysgpi","post_user_id":"5a3daafaedc29549b4bc3bd1","channel":"instagram","author":"justinbieber","created_at":"2023-09-14T00:44:42+00:00","title":"To the most precious, my beloved. 5 years. You have captivated my heart. I know from the depths of my soul down to my bones that this journey with you will only exceed our wildest expectations. So let’s keep dreaming big baby. Cheers to forever and ever. I love you with every fiber of my being. \n\nHAPPY 5TH YEAR ANNIVERSARY!!!","image_url":"https://scontent-sea1-1.cdninstagram.com/v/t51.29350-15/378520140_1363410121238935_7314345943313493557_n.jpg?_nc_cat=110&ccb=1-7&_nc_sid=18de74&_nc_ohc=xf6Dr75REwEAX8RCbhs&_nc_ht=scontent-sea1-1.cdninstagram.com&edm=AL-3X8kEAAAA&oh=00_AfDOxp_dNcuF6vgMDy-2mpCiQqUkb5591RiwenUwp7Oowg&oe=660C0245","avatar":"https://scontent-sea1-1.xx.fbcdn.net/v/t51.2885-15/350507605_1017436996365336_5254999826464604062_n.jpg?_nc_cat=1&ccb=1-7&_nc_sid=7d201b&_nc_ohc=BmjUBhscKkcAX-z1f6d&_nc_ht=scontent-sea1-1.xx&edm=AL-3X8kEAAAA&oh=00_AfDM9ICu4UEvBwN7lZfxaOFs6FrzPZt6dFO_ynUJex1P7w&oe=660B644C","content":null,"is_album":true,"likes":6658583,"comments":55846,"is_business":true,"album_video":["","","","","",""],"album":["https://scontent-ord5-2.cdninstagram.com/v/t51.2885-15/378520140_1363410121238935_7314345943313493557_n.jpg?stp=dst-jpg_e35_s1080x1080&_nc_ht=scontent-ord5-2.cdninstagram.com&_nc_cat=107&_nc_ohc=yw57Q5bfdCsAX9SwWOH&edm=AABBvjUBAAAA&ccb=7-5&oh=00_AfCglVwMHZPgh0LWXc8DM2D9Y8MhqcHA3IcRoexpo7ZS1w&oe=65C2A9A8&_nc_sid=4f4799","https://scontent-ord5-2.cdninstagram.com/v/t51.2885-15/377737186_1977382309328128_7424690325535396394_n.jpg?stp=dst-jpg_e35_s1080x1080&_nc_ht=scontent-ord5-2.cdninstagram.com&_nc_cat=104&_nc_ohc=v6zrRXkZ_TQAX8XBZqN&edm=AABBvjUBAAAA&ccb=7-5&oh=00_AfAqmcFj79zRRUUO9HQc20FrF-Nw1gxGfHyeFn9HmkHa-Q&oe=65C256CB&_nc_sid=4f4799","https://scontent-ord5-1.cdninstagram.com/v/t51.2885-15/377593375_689136989913548_4899600465300850935_n.jpg?stp=dst-jpg_e35_s1080x1080&_nc_ht=scontent-ord5-1.cdninstagram.com&_nc_cat=108&_nc_ohc=VboUeCkxN8YAX95LZNK&edm=AABBvjUBAAAA&ccb=7-5&oh=00_AfC20rs1w9t9T1nct6XS3QYJJlEi5ukDeWkmRmPOE7bpmw&oe=65C23BB8&_nc_sid=4f4799","https://scontent-ord5-1.cdninstagram.com/v/t51.2885-15/377921300_1021814185516916_2978219323572517780_n.jpg?stp=dst-jpg_e35_s1080x1080&_nc_ht=scontent-ord5-1.cdninstagram.com&_nc_cat=108&_nc_ohc=I_xCQ_eVctIAX-YEwRH&edm=AABBvjUBAAAA&ccb=7-5&oh=00_AfC392NXAHnjrP_X48YQ0xiOgbI4Fh9cRDfg63u0_XRmVA&oe=65C3EB02&_nc_sid=4f4799","https://scontent-ord5-2.cdninstagram.com/v/t51.2885-15/377651684_820495569771043_5556187609484573678_n.jpg?stp=dst-jpg_e35_s1080x1080&_nc_ht=scontent-ord5-2.cdninstagram.com&_nc_cat=107&_nc_ohc=EM0gT1BMcrkAX_ktQPd&edm=AABBvjUBAAAA&ccb=7-5&oh=00_AfBynM5funKi8fDgtCky5bauQPbANFtUO2hvQ8l7phe1NQ&oe=65C3EF5E&_nc_sid=4f4799","https://scontent-ord5-2.cdninstagram.com/v/t51.2885-15/377612574_846901360382402_2340967276091274717_n.jpg?stp=dst-jpg_e35_s1080x1080&_nc_ht=scontent-ord5-2.cdninstagram.com&_nc_cat=102&_nc_ohc=_UzfI3U_MqkAX9y_h3U&edm=AABBvjUBAAAA&ccb=7-5&oh=00_AfAiE4VKy3EIMCARmHxW6nXL_CrIyXtF6sHN2T_M1WW0Pw&oe=65C2B21F&_nc_sid=4f4799"],"clean":true,"last_update_time":"2024-02-03T11:04:06.529185","followers":292962550,"max_price":1326937,"min_price":1324821,"location_name":"","location_public":false,"is_video":false,"location_slug":"","location_id":"","brand_mentions":[],"embedded_links":[],"top_comments":[],"sentiment_distribution":{"neg":0,"pos":0,"neu":0},"positive_comments":[],"demos_failed":true,"id":null,"video_url":null}},{"date":1696118400000,"post":{"tiktok_post_id":null,"url":"https://www.instagram.com/p/CzCDXxyvehO","post_user_id":"5a3daafaedc29549b4bc3bd1","channel":"instagram","author":"justinbieber","created_at":"2023-10-30T17:54:31+00:00","title":"amberasaly happy Halloween","image_url":"https://scontent-sea1-1.cdninstagram.com/v/t51.29350-15/397615958_1468156903770414_2729828323258411922_n.jpg?_nc_cat=105&ccb=1-7&_nc_sid=18de74&_nc_ohc=TDV4gohTLb8AX-Axs9N&_nc_ht=scontent-sea1-1.cdninstagram.com&edm=AL-3X8kEAAAA&oh=00_AfD5HnJd0_PZIqktXmHMJeM7Qvan_6BxyCZA_Iu8y5812w&oe=660BC3BA","avatar":"https://scontent-sea1-1.xx.fbcdn.net/v/t51.2885-15/350507605_1017436996365336_5254999826464604062_n.jpg?_nc_cat=1&ccb=1-7&_nc_sid=7d201b&_nc_ohc=BmjUBhscKkcAX-z1f6d&_nc_ht=scontent-sea1-1.xx&edm=AL-3X8kEAAAA&oh=00_AfDM9ICu4UEvBwN7lZfxaOFs6FrzPZt6dFO_ynUJex1P7w&oe=660B644C","content":null,"is_album":true,"likes":5648515,"comments":26912,"is_business":true,"album_video":["","","","",""],"album":["https://instagram.fbom57-1.fna.fbcdn.net/v/t51.2885-15/397615958_1468156903770414_2729828323258411922_n.jpg?stp=dst-jpg_e35_p1080x1080&_nc_ht=instagram.fbom57-1.fna.fbcdn.net&_nc_cat=106&_nc_ohc=AIwf5pl_45wAX8kE9ww&edm=AABBvjUBAAAA&ccb=7-5&oh=00_AfCWIVyXXwybsDEOFFlfHL29pQoPohRdBeBNYTL9EU4B5Q&oe=65C3A15B&_nc_sid=4f4799","https://instagram.fbom57-1.fna.fbcdn.net/v/t51.2885-15/397358915_983948629340904_6636734886099854426_n.jpg?stp=dst-jpg_e35_p1080x1080&_nc_ht=instagram.fbom57-1.fna.fbcdn.net&_nc_cat=100&_nc_ohc=c0TSONx44NMAX-6B_QK&edm=AABBvjUBAAAA&ccb=7-5&oh=00_AfA4RRK62jQP1GoyiYfM_TP3WeT5mij1InoWf8g4ZbgR8w&oe=65C3B662&_nc_sid=4f4799","https://instagram.fbom57-1.fna.fbcdn.net/v/t51.2885-15/397273200_276522181445800_2829572116244465150_n.jpg?stp=dst-jpg_e35&_nc_ht=instagram.fbom57-1.fna.fbcdn.net&_nc_cat=104&_nc_ohc=WAX77sfkxPsAX_AbXXZ&edm=AABBvjUBAAAA&ccb=7-5&oh=00_AfAiXo35oQ6fv0Yg61BhGXYgS_PjhO-a_WDeuxLVrCQgyg&oe=65C26410&_nc_sid=4f4799","https://instagram.fbom57-1.fna.fbcdn.net/v/t51.2885-15/396883716_703270825025175_351500224890820708_n.jpg?stp=dst-jpg_e35_p1080x1080&_nc_ht=instagram.fbom57-1.fna.fbcdn.net&_nc_cat=103&_nc_ohc=ykkaBQdvjYAAX9r_u2C&edm=AABBvjUBAAAA&ccb=7-5&oh=00_AfAIxR-9clBhyRNCZPUgBEWl_f3dH7LRfCZBvzbCkviKAA&oe=65C334AC&_nc_sid=4f4799","https://instagram.fbom57-1.fna.fbcdn.net/v/t51.2885-15/396574909_1478651216227933_8463134518655173402_n.jpg?stp=dst-jpg_e35_p1080x1080&_nc_ht=instagram.fbom57-1.fna.fbcdn.net&_nc_cat=101&_nc_ohc=iLqrUnjrUvoAX9JD3qd&edm=AABBvjUBAAAA&ccb=7-5&oh=00_AfAba-ba2l-UhhduSSVeS3r8myCLRseFCvtUCyaCVG4xVA&oe=65C39604&_nc_sid=4f4799"],"clean":true,"last_update_time":"2024-02-03T11:02:09.368509","followers":292962550,"max_price":1326937,"min_price":1324821,"location_name":"","location_public":false,"is_video":false,"location_slug":"","location_id":"","brand_mentions":[],"embedded_links":[],"top_comments":[],"sentiment_distribution":{"neg":0,"pos":0,"neu":0},"positive_comments":[],"demos_failed":true,"id":null}},{"date":1698796800000,"post":{"tiktok_post_id":null,"url":"https://www.instagram.com/p/Cz10DB_SR1i","post_user_id":"5a3daafaedc29549b4bc3bd1","channel":"instagram","author":"justinbieber","created_at":"2023-11-19T20:21:07","title":"Some cute things ,","image_url":"https://s3-us-west-2.amazonaws.com/crawler.img/655eb30f2f95f22bde6e1acf.jpg","avatar":"https://scontent-sea1-1.xx.fbcdn.net/v/t51.2885-15/350507605_1017436996365336_5254999826464604062_n.jpg?_nc_cat=1&ccb=1-7&_nc_sid=7d201b&_nc_ohc=BmjUBhscKkcAX-z1f6d&_nc_ht=scontent-sea1-1.xx&edm=AL-3X8kEAAAA&oh=00_AfDM9ICu4UEvBwN7lZfxaOFs6FrzPZt6dFO_ynUJex1P7w&oe=660B644C","content":null,"is_album":true,"likes":3576747,"comments":20911,"is_business":true,"album_video":["","","","","https://instagram.fmaa1-4.fna.fbcdn.net/o1/v/t16/f1/m69/GP8eEBhPQk0AxZ0AAIt2WtrtWhtRbkYLAAAF.mp4?efg=eyJxZV9ncm91cHMiOiJbXCJpZ193ZWJfZGVsaXZlcnlfdnRzX290ZlwiXSIsInZlbmNvZGVfdGFnIjoidnRzX3ZvZF91cmxnZW4uY2Fyb3VzZWxfaXRlbS5jMi43MjAuYmFzZWxpbmUifQ&_nc_ht=instagram.fmaa1-4.fna.fbcdn.net&_nc_cat=109&vs=634815575529923_3090591181&_nc_vs=HBksFQIYOnBhc3N0aHJvdWdoX2V2ZXJzdG9yZS9HUDhlRUJoUFFrMEF4WjBBQUl0Mld0cnRXaHRSYmtZTEFBQUYVAALIAQAVAhg6cGFzc3Rocm91Z2hfZXZlcnN0b3JlL0dFX0xBeGl2RnhBSTFGUUJBSURMbkIzWTlDOW5ia1lMQUFBRhUCAsgBACgAGAAbABUAACaMvc7b0daAQBUCKAJDMywXQAJmZmZmZmYYEmRhc2hfYmFzZWxpbmVfMV92MREAde4HAA%3D%3D&ccb=9-4&oh=00_AfAQFFK4x-jUipo35KGczdSOIIn_MUieN_w4vqUmk_s8Eg&oe=660B7969&_nc_sid=4f4799","","","",""],"album":["https://instagram.fmaa1-3.fna.fbcdn.net/v/t51.29350-15/403217126_353955563878816_545490259680057571_n.jpg?stp=dst-jpg_e35_p1080x1080&_nc_ht=instagram.fmaa1-3.fna.fbcdn.net&_nc_cat=104&_nc_ohc=_1VYFeKsPlkAX-ildFx&edm=AABBvjUBAAAA&ccb=7-5&oh=00_AfAisdMM9Cy1vrqVvZJV8eEFPMI7K1ud4ritY88YRBynKQ&oe=660F945E&_nc_sid=4f4799","https://instagram.fmaa1-4.fna.fbcdn.net/v/t51.29350-15/403754010_893538118983254_5818025670628310696_n.jpg?stp=dst-jpg_e35_p1080x1080&_nc_ht=instagram.fmaa1-4.fna.fbcdn.net&_nc_cat=102&_nc_ohc=Hixu8xqM69gAX8YE4UL&edm=AABBvjUBAAAA&ccb=7-5&oh=00_AfB-LsExdo5ou3BPB09P5m--a_CGtmNqiZ5LEPWf4f_W2A&oe=660F6866&_nc_sid=4f4799","https://instagram.fmaa1-4.fna.fbcdn.net/v/t51.29350-15/403808755_354668183808974_5118824157330165060_n.jpg?stp=dst-jpg_e35_p1080x1080&_nc_ht=instagram.fmaa1-4.fna.fbcdn.net&_nc_cat=102&_nc_ohc=x8WFtpr4KQwAX_X2lYK&edm=AABBvjUBAAAA&ccb=7-5&oh=00_AfDpp21dlXTU3MUjhV4cjW7DG-nM4l0T9tVQT3RTKksOoA&oe=660F7EAA&_nc_sid=4f4799","https://instagram.fmaa1-1.fna.fbcdn.net/v/t51.29350-15/403722528_592509212972831_3195771695872362049_n.jpg?stp=dst-jpg_e35_p1080x1080&_nc_ht=instagram.fmaa1-1.fna.fbcdn.net&_nc_cat=111&_nc_ohc=di7Ln9jOrJ0AX9S2ka3&edm=AABBvjUBAAAA&ccb=7-5&oh=00_AfBxi6z2CdqljJOZJxtg0r8queVZxVNlJ6fryYculNIZLg&oe=660F773F&_nc_sid=4f4799","https://instagram.fmaa1-3.fna.fbcdn.net/v/t51.29350-15/403880410_1998518737201829_3939241241448379433_n.jpg?stp=dst-jpg_e15&_nc_ht=instagram.fmaa1-3.fna.fbcdn.net&_nc_cat=105&_nc_ohc=pLPqNRBKHXQAX-bDvUc&edm=AABBvjUBAAAA&ccb=7-5&oh=00_AfDf1H4nxee_sZGp9wwYcpOERcn6_Tk1XqW51X7tS-zAVA&oe=660B8914&_nc_sid=4f4799","https://instagram.fmaa1-2.fna.fbcdn.net/v/t51.29350-15/404020330_357280056801303_6660250977137704618_n.jpg?stp=dst-jpg_e35_p1080x1080&_nc_ht=instagram.fmaa1-2.fna.fbcdn.net&_nc_cat=103&_nc_ohc=B4QkYuX2UtoAX_vK2jN&edm=AABBvjUBAAAA&ccb=7-5&oh=00_AfCKSKJ1xXA61DpAGP2hWqrtIE78wfv8lAy_tWkKKBZgOg&oe=660F9230&_nc_sid=4f4799","https://instagram.fmaa1-3.fna.fbcdn.net/v/t51.29350-15/403454300_206334879175708_1847071941376579438_n.jpg?stp=dst-jpg_e35_p1080x1080&_nc_ht=instagram.fmaa1-3.fna.fbcdn.net&_nc_cat=104&_nc_ohc=lsr_vD8vrBwAX_kFcgm&edm=AABBvjUBAAAA&ccb=7-5&oh=00_AfCuckjqlZM1vIypYWjFXtTDKD0j6NsGQr5kMnQCHsW1hg&oe=660F6C29&_nc_sid=4f4799","https://instagram.fmaa1-1.fna.fbcdn.net/v/t51.29350-15/403175951_1655310578292708_292054973243883032_n.jpg?stp=dst-jpg_e35_p1080x1080&_nc_ht=instagram.fmaa1-1.fna.fbcdn.net&_nc_cat=100&_nc_ohc=3syX5_iHZJ0AX8m2fUC&edm=AABBvjUBAAAA&ccb=7-5&oh=00_AfAtIPsaWfQPjKHUR4VIYaE8nl3fWbmnv7gor78tFZ1JEg&oe=660F7B0A&_nc_sid=4f4799","https://instagram.fmaa1-4.fna.fbcdn.net/v/t51.29350-15/403917932_347584857959534_5795564026885190410_n.jpg?stp=dst-jpg_e35_p1080x1080&_nc_ht=instagram.fmaa1-4.fna.fbcdn.net&_nc_cat=102&_nc_ohc=Q4cqXyrAzYwAX-hWGjD&edm=AABBvjUBAAAA&ccb=7-5&oh=00_AfD1-df2kufcgz-BB69ckvzeDVqcFiNxQ1NFrzaz704XfA&oe=660F64B2&_nc_sid=4f4799"],"clean":true,"last_update_time":"2024-03-31T18:04:36.017624","followers":292936338,"max_price":1326944,"min_price":1324828,"location_name":"","location_public":false,"is_video":false,"location_slug":"","location_id":"","brand_mentions":[],"embedded_links":[],"top_comments":[],"sentiment_distribution":{"neg":0,"pos":0,"neu":0},"positive_comments":[],"demos_failed":true,"id":null,"video_url":null}},{"date":1701388800000,"post":{"tiktok_post_id":null,"url":"https://www.instagram.com/p/C1a2pAVMu4q","post_user_id":"5a3daafaedc29549b4bc3bd1","channel":"instagram","author":"justinbieber","created_at":"2023-12-29T02:07:04","title":"Had fun last night at the next gen game with the @mapleleafs","image_url":"https://s3-us-west-2.amazonaws.com/crawler.img/658f5dfe4433fad9cd515c9a.jpg","avatar":"https://scontent-sea1-1.xx.fbcdn.net/v/t51.2885-15/350507605_1017436996365336_5254999826464604062_n.jpg?_nc_cat=1&ccb=1-7&_nc_sid=7d201b&_nc_ohc=BmjUBhscKkcAX-z1f6d&_nc_ht=scontent-sea1-1.xx&edm=AL-3X8kEAAAA&oh=00_AfDM9ICu4UEvBwN7lZfxaOFs6FrzPZt6dFO_ynUJex1P7w&oe=660B644C","content":null,"is_album":true,"likes":2738989,"comments":15836,"is_business":true,"album_video":["",""],"album":["https://instagram.fdel27-2.fna.fbcdn.net/v/t51.29350-15/413473478_3368359920122621_193556914051953760_n.jpg?stp=dst-jpg_e35_s1080x1080&_nc_ht=instagram.fdel27-2.fna.fbcdn.net&_nc_cat=105&_nc_ohc=XJdtp53IGnkAX_uy_gI&edm=AABBvjUBAAAA&ccb=7-5&oh=00_AfDPPkK0HvpJXQjnD7T3va-Sc4UdYEGyReH3hCFQSpxLUA&oe=660F5D5C&_nc_sid=4f4799","https://instagram.fdel27-4.fna.fbcdn.net/v/t51.29350-15/412725821_747506103911304_4722570595515257478_n.jpg?stp=dst-jpg_e35_s1080x1080&_nc_ht=instagram.fdel27-4.fna.fbcdn.net&_nc_cat=100&_nc_ohc=ZIc0018JV5QAX8g5jkQ&edm=AABBvjUBAAAA&ccb=7-5&oh=00_AfAUZpiw2kNndO1nMqDpcbC__iAX_ZsBkMzwy10RaNlvOA&oe=660F63CC&_nc_sid=4f4799"],"clean":true,"last_update_time":"2024-03-31T18:03:41.002265","followers":292936338,"max_price":1326944,"min_price":1324828,"location_name":"","location_public":false,"is_video":false,"location_slug":"","location_id":"","brand_mentions":[{"name":"Next","logo":"https://superboostaa.s3.us-west-2.amazonaws.com/next_1626244838216.jpg","key":"next"},{"name":"The Last of Us","logo":"https://superboostaa.s3.us-west-2.amazonaws.com/the-last-of-us_1626245099213.jpg","key":"the-last-of-us"}],"embedded_links":[],"top_comments":[],"sentiment_distribution":{"neg":0,"pos":0,"neu":0},"positive_comments":[],"demos_failed":true,"id":null,"video_url":null}},{"date":1704067200000,"post":{"tiktok_post_id":null,"url":"https://www.instagram.com/p/C2vkCLTvRj6","post_user_id":"5a3daafaedc29549b4bc3bd1","channel":"instagram","author":"justinbieber","created_at":"2024-01-30T23:39:56","title":"","image_url":"https://s3-us-west-2.amazonaws.com/crawler.img/65b9d2ba49f59048049abff5.jpg","avatar":"https://scontent-sea1-1.xx.fbcdn.net/v/t51.2885-15/350507605_1017436996365336_5254999826464604062_n.jpg?_nc_cat=1&ccb=1-7&_nc_sid=7d201b&_nc_ohc=BmjUBhscKkcAX-z1f6d&_nc_ht=scontent-sea1-1.xx&edm=AL-3X8kEAAAA&oh=00_AfDM9ICu4UEvBwN7lZfxaOFs6FrzPZt6dFO_ynUJex1P7w&oe=660B644C","content":null,"likes":4969706,"comments":29187,"is_business":true,"clean":true,"album":["https://instagram.fhyd1-2.fna.fbcdn.net/v/t51.29350-15/424627720_915178010280788_6939657716594545143_n.jpg?stp=dst-jpg_e35_p1080x1080&_nc_ht=instagram.fhyd1-2.fna.fbcdn.net&_nc_cat=108&_nc_ohc=55iS30tKjgkAX9h6LSC&edm=AABBvjUBAAAA&ccb=7-5&oh=00_AfBkOejBModQdgEBPcqZwgSEgtFVhfTbXk5NWjpSkpGS3g&oe=660F7529&_nc_sid=4f4799","https://instagram.fhyd1-4.fna.fbcdn.net/v/t51.29350-15/424503466_1049338956179870_3089689787652021399_n.jpg?stp=dst-jpg_e35_p1080x1080&_nc_ht=instagram.fhyd1-4.fna.fbcdn.net&_nc_cat=102&_nc_ohc=4LMWD2dERe8AX_Ikzm_&edm=AABBvjUBAAAA&ccb=7-5&oh=00_AfBpzU30sTBqQdFL5PwcjyISqZ54_3aE0QqS5fY3bk0pQg&oe=660F8403&_nc_sid=4f4799","https://instagram.fhyd1-4.fna.fbcdn.net/v/t51.29350-15/424558156_751646659865306_7440954234605683606_n.jpg?stp=dst-jpg_e35_p1080x1080&_nc_ht=instagram.fhyd1-4.fna.fbcdn.net&_nc_cat=102&_nc_ohc=aiqLVqi8QEAAX-cVqgr&edm=AABBvjUBAAAA&ccb=7-5&oh=00_AfBtrQTLd5NbJKMp1rHPvygBVbu8xg0YuDXpdq3SWSPERg&oe=660F6F6F&_nc_sid=4f4799"],"is_album":true,"album_video":["","",""],"last_update_time":"2024-03-31T17:58:44.652064","followers":292936338,"max_price":1326944,"min_price":1324828,"location_name":"","location_public":false,"is_video":false,"location_slug":"","location_id":"","brand_mentions":[],"embedded_links":[],"top_comments":[],"sentiment_distribution":{"neg":0,"pos":0,"neu":0},"positive_comments":[],"demos_failed":true,"video_url":null}},{"date":1706745600000,"post":{"tiktok_post_id":null,"url":"https://www.instagram.com/p/C3QdEP9vBEM","post_user_id":"5a3daafaedc29549b4bc3bd1","channel":"instagram","author":"justinbieber","created_at":"2024-02-12T18:13:59","title":"LOVE YOU MY BROTHER\n\nNOONE CAN SING AND DANCE THE WAY YOU DO.\n\nLOVE YOU FROM THE DEPTHS OF MY HEART.\n\nBROUGHT THE “A” TO THE WORLD, \n\nONLY YOU BABYYYYYY 😘","image_url":"https://s3-us-west-2.amazonaws.com/crawler.img/65caedb6890c37d63e30c3da.jpg","avatar":"https://scontent-sea1-1.xx.fbcdn.net/v/t51.2885-15/350507605_1017436996365336_5254999826464604062_n.jpg?_nc_cat=1&ccb=1-7&_nc_sid=7d201b&_nc_ohc=BmjUBhscKkcAX-z1f6d&_nc_ht=scontent-sea1-1.xx&edm=AL-3X8kEAAAA&oh=00_AfDM9ICu4UEvBwN7lZfxaOFs6FrzPZt6dFO_ynUJex1P7w&oe=660B644C","content":null,"likes":2677190,"comments":26614,"is_business":true,"clean":true,"last_update_time":"2024-03-31T18:09:13.438968","followers":292936338,"max_price":1326944,"min_price":1324828,"location_name":"","location_public":false,"is_video":false,"album":[],"album_video":[],"location_slug":"","location_id":"","brand_mentions":[],"embedded_links":[],"top_comments":[],"sentiment_distribution":{"neg":0,"pos":0,"neu":0},"positive_comments":[],"demos_failed":true,"video_url":null}},{"date":1709251200000,"post":{"tiktok_post_id":null,"url":"https://www.instagram.com/reel/C4OnUS2vBaG","post_user_id":"5a3daafaedc29549b4bc3bd1","channel":"instagram","author":"justinbieber","created_at":"2024-03-07T21:38:26","title":"DOWNLOAD THE CHURCHOME APP FOR MORE GUIDED PRAYERS AND MOREEEEEEEEEE  LINK IN BIO🫠🫠🫠🫠🫠😍😍😍","image_url":"https://s3-us-west-2.amazonaws.com/crawler.img/65eb45e4272dfd21ba373ca2.jpg","avatar":"https://scontent-sea1-1.xx.fbcdn.net/v/t51.2885-15/350507605_1017436996365336_5254999826464604062_n.jpg?_nc_cat=1&ccb=1-7&_nc_sid=7d201b&_nc_ohc=BmjUBhscKkcAX-z1f6d&_nc_ht=scontent-sea1-1.xx&edm=AL-3X8kEAAAA&oh=00_AfDM9ICu4UEvBwN7lZfxaOFs6FrzPZt6dFO_ynUJex1P7w&oe=660B644C","content":null,"likes":588834,"comments":14211,"is_video":true,"is_business":true,"clean":true,"last_update_time":"2024-03-31T18:12:07.474999","followers":292936338,"max_price":1326944,"min_price":1324828,"location_name":"","location_public":false,"video_url":"https://instagram.fccu4-3.fna.fbcdn.net/v/t66.30100-16/10000000_1360123071368535_8090276032751166412_n.mp4?_nc_ht=instagram.fccu4-3.fna.fbcdn.net&_nc_cat=103&_nc_ohc=aOjhwSfIC98AX8U2cnd&edm=AABBvjUBAAAA&ccb=7-5&oh=00_AfC_tpDTovhygeTGLfd1gShtujBWwV6FDIXfdaaYrUolLQ&oe=660B6CD0&_nc_sid=4f4799","album":[],"album_video":[],"location_slug":"","views":3691005,"location_id":""}}]}