{"data":{"followers":[{"date":1648771200000,"value":75770230},{"date":1651363200000,"value":76941101},{"date":1654041600000,"value":78698930},{"date":1656633600000,"value":80089457},{"date":1659312000000,"value":80825475},{"date":1661990400000,"value":81654644},{"date":1664582400000,"value":82611350},{"date":1667260800000,"value":83181795},{"date":1669852800000,"value":83828951},{"date":1672531200000,"value":84324795},{"date":1675209600000,"value":84878973},{"date":1677628800000,"value":85442140},{"date":1680307200000,"value":86129220},{"date":1682899200000,"value":87014760},{"date":1685577600000,"value":87889567},{"date":1688169600000,"value":88425869},{"date":1690848000000,"value":88716374},{"date":1693526400000,"value":89070848},{"date":1696118400000,"value":89531117},{"date":1698796800000,"value":89809626},{"date":1701388800000,"value":89949414},{"date":1704067200000,"value":90224705}],"views":[],"increase_views":[],"increase_followers":[{"date":1651363200000,"value":1170871},{"date":1654041600000,"value":1757829},{"date":1656633600000,"value":1390527},{"date":1659312000000,"value":736018},{"date":1661990400000,"value":829169},{"date":1664582400000,"value":956706},{"date":1667260800000,"value":570445},{"date":1669852800000,"value":647156},{"date":1672531200000,"value":495844},{"date":1675209600000,"value":554178},{"date":1677628800000,"value":563167},{"date":1680307200000,"value":687080},{"date":1682899200000,"value":885540},{"date":1685577600000,"value":874807},{"date":1688169600000,"value":536302},{"date":1690848000000,"value":290505},{"date":1693526400000,"value":354474},{"date":1696118400000,"value":460269},{"date":1698796800000,"value":278509},{"date":1701388800000,"value":139788},{"date":1704067200000,"value":275291}]},"post_data":[{"date":1648771200000,"post":{"tiktok_post_id":null,"url":"https://www.instagram.com/p/Ccd9JA4Pxwi","post_user_id":"5a3f8fecedc2956dd5bb6ff0","channel":"instagram","author":"priyankachopra","created_at":"2022-04-17T21:56:44+00:00","title":"Happy Easter from us. \n🐣❤️🥰","image_url":"https://scontent-sea1-1.cdninstagram.com/v/t51.29350-15/278507720_346228884147557_2577704948783908619_n.jpg?_nc_cat=108&ccb=1-7&_nc_sid=8ae9d6&_nc_ohc=kNENkyEdICEAX9GowTH&_nc_ht=scontent-sea1-1.cdninstagram.com&edm=AL-3X8kEAAAA&oh=00_AT8Q3LRZNBhqZxAkDipVJwEE0kdnzWDb4RJNFVr_RVE62A&oe=635A7D04","avatar":"https://scontent-sea1-1.xx.fbcdn.net/v/t51.2885-15/260072688_709901617053639_4589312489854672734_n.jpg?_nc_cat=1&ccb=1-7&_nc_sid=86c713&_nc_ohc=1qcUG1YucaIAX_0cYs7&_nc_ht=scontent-sea1-1.xx&edm=AL-3X8kEAAAA&oh=00_AT8Q_xUzr2qsSuEl9qrWbOg0GGdjTK24FlHilWgeqBvL9A&oe=6357ADBA","content":null,"likes":3192527,"comments":6281,"is_business":true,"is_new":false,"clean":true,"last_update_time":"2022-10-14T06:37:06.738846","followers":82910855,"max_price":227582,"min_price":227436,"location_name":"","location_public":false,"is_video":false,"album":["https://instagram.ffjr1-1.fna.fbcdn.net/v/t51.2885-15/278507720_346228884147557_2577704948783908619_n.jpg?stp=dst-jpg_e35_p1080x1080&_nc_ht=instagram.ffjr1-1.fna.fbcdn.net&_nc_cat=105&_nc_ohc=bQzmAtECqbUAX-qaSYj&edm=AABBvjUBAAAA&ccb=7-5&oh=00_AT_F3BTb2gcbtNyxSZdvkcx8SWCijKCOIQOewfGNzvlYjA&oe=634F4986&_nc_sid=83d603","https://instagram.ffjr1-5.fna.fbcdn.net/v/t51.2885-15/278653341_1180038949413827_8989917245323598087_n.jpg?stp=dst-jpg_e35_p1080x1080&_nc_ht=instagram.ffjr1-5.fna.fbcdn.net&_nc_cat=111&_nc_ohc=glwNbpR4eYEAX-GiORc&edm=AABBvjUBAAAA&ccb=7-5&oh=00_AT8982-Ktjj57kt_rKQOR52xr_cIpTQZmxJeTk4FXF1L8g&oe=634F4196&_nc_sid=83d603","https://instagram.ffjr1-5.fna.fbcdn.net/v/t51.2885-15/278579526_1438047856628567_7648990559998728418_n.jpg?stp=dst-jpg_e35_p1080x1080&_nc_ht=instagram.ffjr1-5.fna.fbcdn.net&_nc_cat=111&_nc_ohc=9X7xnSzKEFoAX8umMms&edm=AABBvjUBAAAA&ccb=7-5&oh=00_AT_sTbENysa17pzf1pF55vCSlsXJrfeBJAx1CUtt6dT2Cg&oe=6350A3D0&_nc_sid=83d603","https://instagram.ffjr1-1.fna.fbcdn.net/v/t51.2885-15/278675909_554659255975457_6161256335641148056_n.jpg?stp=dst-jpg_e35_p1080x1080&_nc_ht=instagram.ffjr1-1.fna.fbcdn.net&_nc_cat=105&_nc_ohc=8fevyn3rfbIAX9BE6Dj&edm=AABBvjUBAAAA&ccb=7-5&oh=00_AT-2T3-svhJIV0NlbjEVesZJvOxuV1KHk9DAoQ0JRCju0g&oe=634F0924&_nc_sid=83d603","https://instagram.ffjr1-4.fna.fbcdn.net/v/t51.2885-15/278568593_963556664351959_2372832505472909938_n.jpg?stp=dst-jpg_e35_p1080x1080&_nc_ht=instagram.ffjr1-4.fna.fbcdn.net&_nc_cat=107&_nc_ohc=PLLmf7D-6wcAX8qizJq&edm=AABBvjUBAAAA&ccb=7-5&oh=00_AT9jKF19Kl4MZSVdaqNtS9EVLaiitbX8LOMBDZleeFzGrQ&oe=634F7499&_nc_sid=83d603"],"location_slug":"","location_id":"","last_comment_ref":"17926888838454130"}},{"date":1651363200000,"post":{"tiktok_post_id":null,"url":"https://www.instagram.com/p/CdTr_YnvMkp","post_user_id":"5a3f8fecedc2956dd5bb6ff0","channel":"instagram","author":"priyankachopra","created_at":"2022-05-08T18:45:52+00:00","title":"On this Mother’s Day we can’t help but reflect on these last few months and the rollercoaster we’ve been on, which we now know, so many people have also experienced. After 100 plus days in the NICU, our little girl is finally home. Every family’s journey is unique and requires a certain level of faith, and while ours was a challenging few months, what becomes abundantly clear, in retrospect, is how precious and perfect every moment is. We are overjoyed that our little girl is finally home, and just want to thank every Doctor, nurse and specialist at Rady Children’s La Jolla and Cedar Sinai, Los Angeles, who were there selflessly every step of the way. Our next chapter begins now, and our baby is truly a badass. Let’s get it MM! Mommy and Daddy love you. \n\nHappy Mother’s Day to all the mothers and caretakers in my life and out there. You make it look so easy. Thank you. \n\nAlso.. there is no one I’d rather do this with than you. Thank you for making me a mama nickjonas I love you ❤️\n\nPs- thx divya_jyoti masi for the picture and akarikalai masi for MMs fit!\n\nॐ नमः शिवाय","image_url":"https://scontent-sea1-1.cdninstagram.com/v/t51.29350-15/280067218_400765025249678_4004389256659499962_n.jpg?_nc_cat=111&ccb=1-7&_nc_sid=8ae9d6&_nc_ohc=2ln4T7K2EDIAX_q5CG9&_nc_ht=scontent-sea1-1.cdninstagram.com&edm=AL-3X8kEAAAA&oh=00_AfDjgKhJWFwDmo8sqDtiOC1AgVrDnghiA_ZbfbsNO_82MA&oe=636B1B4D","avatar":"https://scontent-sea1-1.xx.fbcdn.net/v/t51.2885-15/260072688_709901617053639_4589312489854672734_n.jpg?_nc_cat=1&ccb=1-7&_nc_sid=86c713&_nc_ohc=8MQDqNS18uMAX-Fp3O5&_nc_ht=scontent-sea1-1.xx&edm=AL-3X8kEAAAA&oh=00_AfAHi9nb9h5aHIt59XoFVWkK7NMju6hYRf0Y73PS9covqg&oe=636979FA","content":null,"likes":4322163,"comments":20995,"is_business":true,"clean":true,"last_update_time":"2022-11-02T15:21:03.669322","followers":83204513,"max_price":227582,"min_price":227436,"location_name":"Los Angeles, California","location_public":true,"is_video":false,"album":[],"location_slug":"los-angeles-california","location_id":"212999109","last_comment_ref":"17991782533529035","is_new":false,"id":null}},{"date":1654041600000,"post":{"tiktok_post_id":null,"url":"https://www.instagram.com/p/Cee2L89JJme","post_user_id":"5a3f8fecedc2956dd5bb6ff0","channel":"instagram","author":"priyankachopra","created_at":"2022-06-06T23:18:00","title":"And then there was us.. girls just wanna have fun!❤️ @bulgari @lalalalisa_m @annehathaway","image_url":"https://s3-us-west-2.amazonaws.com/crawler.img/629ec481bbba454e1494c961.jpg","avatar":"https://scontent-sea1-1.xx.fbcdn.net/v/t51.2885-15/260072688_709901617053639_4589312489854672734_n.jpg?_nc_cat=1&ccb=1-7&_nc_sid=86c713&_nc_eui2=AeG9iGAfuHuiHIDi_srsvCq5s76twZ2IbW-zvq3BnYhtb1m2kpPAVrQl3ZrvtZhBlmdRXWtcIH-A_mrY_hUj3pf3&_nc_ohc=8MQDqNS18uMAX-Fp3O5&_nc_ht=scontent-sea1-1.xx&edm=AL-3X8kEAAAA&oh=00_AfCjxzb0lF-B6tJIJfRfRJQZRF1AABCVLIkIR-h1eu54bQ&oe=636D6E7A","content":null,"likes":3140026,"comments":24657,"is_business":true,"is_new":false,"clean":true,"last_update_time":"2022-11-10T04:04:44.283107","followers":83255007,"max_price":227582,"min_price":227436,"location_name":"","location_public":false,"is_video":false,"album":[],"location_slug":"","location_id":"","last_comment_ref":"17967698536784046"}},{"date":1656633600000,"post":{"tiktok_post_id":null,"url":"https://www.instagram.com/p/CgUi7zirtpq","post_user_id":"5a3f8fecedc2956dd5bb6ff0","channel":"instagram","author":"priyankachopra","created_at":"2022-07-22T16:20:09+00:00","title":"Just a girl and her birthday squad! ✨ \n\nSo grateful and thankful to be surrounded by so much love and to be able to spend time with my nearest and dearest. (Even though a lot of them flew in from very far). \n\nThe most incredible celebrations, planned and executed to perfection by my ♥️ nickjonas. Words are not enough to thank you for the most memorable birthday… you really know how to love baby. I’m a lucky girl🫶🏽💕\n\nI'm so touched by all the birthday love I've received this year. 🫶🏽The lovely DMs, surprises, calls, texts, and big hugs made the day even brighter and made me feel truly special. Thank you everyone who reached out, it means the world.\nHere’s to the beginning of the rest of my life. \n\nGrateful and blessed 🥹❤️","image_url":"https://scontent-sea1-1.cdninstagram.com/v/t51.29350-15/295121802_165187046026168_2699652604497004557_n.jpg?_nc_cat=110&ccb=1-7&_nc_sid=8ae9d6&_nc_ohc=2AdS7q1kMAcAX9rq8c_&_nc_ht=scontent-sea1-1.cdninstagram.com&edm=AL-3X8kEAAAA&oh=00_AfDfOy7ZFWKEXP7nnVg0BdxmJ42uACpZwWoBq68UqKQE3A&oe=63E55C87","avatar":"https://scontent-sea1-1.xx.fbcdn.net/v/t51.2885-15/326344969_935622871150791_3062520831073573062_n.jpg?_nc_cat=1&ccb=1-7&_nc_sid=86c713&_nc_ohc=d09uQrtX8lsAX87fVLH&_nc_ht=scontent-sea1-1.xx&edm=AL-3X8kEAAAA&oh=00_AfCVY_oQGxrm3e-mY0lxrgp5CC8H7KoKVGNh3mKRR4oewg&oe=63E475F6","content":null,"likes":1659023,"comments":4133,"is_business":true,"clean":true,"last_update_time":"2023-01-18T08:06:50.874910","followers":84567014,"max_price":227582,"min_price":227436,"location_name":"Cabo San Lucas,Mexico","location_public":true,"is_video":false,"album":["https://instagram.fyyz1-1.fna.fbcdn.net/v/t51.2885-15/295121802_165187046026168_2699652604497004557_n.jpg?stp=dst-jpg_e35_p1080x1080&_nc_ht=instagram.fyyz1-1.fna.fbcdn.net&_nc_cat=104&_nc_ohc=bpqAYMpD10AAX8ms4Z7&edm=AABBvjUBAAAA&ccb=7-5&oh=00_AfCKgjK4R1vljO38IKrccGxXmwgGQoeQXOylhKFSSkFOIg&oe=63CD5881&_nc_sid=83d603","https://instagram.fyyz1-1.fna.fbcdn.net/v/t51.2885-15/294833135_425909529554017_5846195222746826404_n.jpg?stp=dst-jpg_e35_p1080x1080&_nc_ht=instagram.fyyz1-1.fna.fbcdn.net&_nc_cat=101&_nc_ohc=JfMxDkS9PEYAX-g71Kj&edm=AABBvjUBAAAA&ccb=7-5&oh=00_AfCBzeWQZ0M0NHKeq7hAqqZ_Zto1jRY7cIVwc94cRep09g&oe=63CBD9E6&_nc_sid=83d603","https://instagram.fyyz1-1.fna.fbcdn.net/v/t51.2885-15/295421132_801540041110265_7363734268897799798_n.jpg?stp=dst-jpg_e35_p1080x1080&_nc_ht=instagram.fyyz1-1.fna.fbcdn.net&_nc_cat=105&_nc_ohc=6HwyJg2eC38AX8_JU5H&edm=AABBvjUBAAAA&ccb=7-5&oh=00_AfBI54RO9F6cs50QredCCfh7idxMg4ed1ZSuRpb5NKqv7A&oe=63CC6A6E&_nc_sid=83d603","https://instagram.fyyz1-2.fna.fbcdn.net/v/t51.2885-15/294812288_1446034085897587_3656275509639531856_n.jpg?stp=dst-jpg_e35_p1080x1080&_nc_ht=instagram.fyyz1-2.fna.fbcdn.net&_nc_cat=107&_nc_ohc=e_BLrCu8nDcAX-cufdf&edm=AABBvjUBAAAA&ccb=7-5&oh=00_AfC2sNnBhlrDWlI75vxnqj5YvMG1X2vmUbnvIOpNAB359A&oe=63CC0663&_nc_sid=83d603","https://instagram.fyyz1-1.fna.fbcdn.net/v/t51.2885-15/295527572_1701288866893622_133410569682280378_n.jpg?stp=dst-jpg_e35_p1080x1080&_nc_ht=instagram.fyyz1-1.fna.fbcdn.net&_nc_cat=102&_nc_ohc=RD8DcSVShZoAX-fjc3t&edm=AABBvjUBAAAA&ccb=7-5&oh=00_AfBw-NEOvZT4UIXDykxHxcYAsVQBJ7Q-cZi-WlRHBUjsvA&oe=63CC1FF5&_nc_sid=83d603","https://instagram.fyyz1-2.fna.fbcdn.net/v/t51.2885-15/295064369_343603337988562_1070578392732455135_n.jpg?stp=dst-jpg_e35_p1080x1080&_nc_ht=instagram.fyyz1-2.fna.fbcdn.net&_nc_cat=110&_nc_ohc=3E4uQXJ9wbwAX9a8oTS&edm=AABBvjUBAAAA&ccb=7-5&oh=00_AfA7SztKNJBDBOM4kcMAHn1vyAZ-CntXGtLj0cL4yMe6EA&oe=63CD87E0&_nc_sid=83d603","https://instagram.fyyz1-1.fna.fbcdn.net/v/t51.2885-15/295209750_123542906879073_2511491461326094967_n.jpg?stp=dst-jpg_e35_p1080x1080&_nc_ht=instagram.fyyz1-1.fna.fbcdn.net&_nc_cat=109&_nc_ohc=sGN-u8o1Vs4AX8ykLAF&edm=AABBvjUBAAAA&ccb=7-5&oh=00_AfCRny2TdTdH8MBPnZqEGVaQ4wQ-50tnwlHJkg2FeVUuEw&oe=63CC2DB9&_nc_sid=83d603","https://instagram.fyyz1-1.fna.fbcdn.net/v/t51.2885-15/295015354_558222505959531_2391865503369089881_n.jpg?stp=dst-jpg_e35_p1080x1080&_nc_ht=instagram.fyyz1-1.fna.fbcdn.net&_nc_cat=103&_nc_ohc=fe7ebfKr4YgAX_BPmA4&edm=AABBvjUBAAAA&ccb=7-5&oh=00_AfD2lxtzqI9jJ40cRte1yn2UQ56z6okY1_m4WC_dZ7Lseg&oe=63CD09C0&_nc_sid=83d603","https://instagram.fyyz1-2.fna.fbcdn.net/v/t51.2885-15/294961545_449995110315871_5632715424794275720_n.jpg?stp=dst-jpg_e35_p1080x1080&_nc_ht=instagram.fyyz1-2.fna.fbcdn.net&_nc_cat=107&_nc_ohc=JSrXeW-LwX8AX9VCFEz&edm=AABBvjUBAAAA&ccb=7-5&oh=00_AfD9HQvqIOJ3CzXvzCIDAds8cZ_yal9e2x_xMn2NQh-rKg&oe=63CC6991&_nc_sid=83d603","https://instagram.fyyz1-1.fna.fbcdn.net/v/t51.2885-15/294856930_2679907582144593_3814678008605273751_n.jpg?stp=dst-jpg_e35_p1080x1080&_nc_ht=instagram.fyyz1-1.fna.fbcdn.net&_nc_cat=109&_nc_ohc=wwaOgPcalkUAX8JFHKV&edm=AABBvjUBAAAA&ccb=7-5&oh=00_AfBOCiN5wEgU3JbEHPiDQcCyPI6FSKUJ50XVyqmdMfXiAw&oe=63CC125D&_nc_sid=83d603"],"location_slug":"cabo-san-lucasmexico","location_id":"713809241","last_comment_ref":"18314028313055355"}},{"date":1659312000000,"post":{"tiktok_post_id":null,"url":"https://www.instagram.com/p/ChiHG4JhsxP","post_user_id":"5a3f8fecedc2956dd5bb6ff0","channel":"instagram","author":"priyankachopra","created_at":"2022-08-21T19:17:46+00:00","title":"Love like no other ❤️","image_url":"https://scontent-sjc3-1.cdninstagram.com/v/t51.29350-15/300409119_1201012540471988_2512690257367791721_n.jpg?_nc_cat=109&ccb=1-7&_nc_sid=8ae9d6&_nc_ohc=V908JH7r054AX81D8nN&_nc_ht=scontent-sjc3-1.cdninstagram.com&edm=AL-3X8kEAAAA&oh=00_AfAiFE8A_a9YZodvefhp0ad4t7XMDjTmBEJsWlmpyawHoQ&oe=640FCF8F","avatar":"https://scontent-sjc3-1.xx.fbcdn.net/v/t51.2885-15/333394199_575867377919749_6203459700522284722_n.jpg?_nc_cat=1&ccb=1-7&_nc_sid=86c713&_nc_ohc=JmAz_lYjvrAAX9u85V8&_nc_ht=scontent-sjc3-1.xx&edm=AL-3X8kEAAAA&oh=00_AfCH60A2EgkvdOJhTgsUwAP-k7PQD9oO55V5d9lclGs2cQ&oe=640C81C4","content":null,"likes":3496127,"comments":10423,"is_business":true,"clean":true,"last_update_time":"2023-03-02T11:06:42.897461","followers":85415343,"max_price":102905,"min_price":101633,"location_name":"Los Angeles, California","location_public":true,"is_video":false,"album":["https://instagram.fskt2-1.fna.fbcdn.net/v/t51.2885-15/300409119_1201012540471988_2512690257367791721_n.jpg?stp=dst-jpg_e35_p1080x1080&_nc_ht=instagram.fskt2-1.fna.fbcdn.net&_nc_cat=108&_nc_ohc=3rkeqiwl1x4AX95-7kC&edm=AABBvjUBAAAA&ccb=7-5&oh=00_AfAj6lL0MKL819G3E0yrHaTL4X6WwSQXcpqNw5W8txgxyg&oe=64058EAE&_nc_sid=83d603","https://instagram.fskt2-1.fna.fbcdn.net/v/t51.2885-15/300860576_122906547006652_4453456424233688592_n.jpg?stp=dst-jpg_e35_p1080x1080&_nc_ht=instagram.fskt2-1.fna.fbcdn.net&_nc_cat=104&_nc_ohc=t__Ttsl1M7YAX97iiGY&edm=AABBvjUBAAAA&ccb=7-5&oh=00_AfDwA1phEbTEifmuO3yzgzBDUJJ29cTqh7UqDe0RpLpv8A&oe=6405B57F&_nc_sid=83d603"],"location_slug":"los-angeles-california","location_id":"212999109","last_comment_ref":"17905852598581384","id":null}},{"date":1661990400000,"post":{"tiktok_post_id":null,"url":"https://www.instagram.com/p/CiuuwoFr4aE","post_user_id":"5a3f8fecedc2956dd5bb6ff0","channel":"instagram","author":"priyankachopra","created_at":"2022-09-20T13:26:32","title":"Our first trip to the big 🍎😍🧿","image_url":"https://s3-us-west-2.amazonaws.com/crawler.img/632add08fc9b088c9bcc758b.jpg","avatar":"https://scontent-sea1-1.xx.fbcdn.net/v/t51.2885-15/333394199_575867377919749_6203459700522284722_n.jpg?_nc_cat=1&ccb=1-7&_nc_sid=86c713&_nc_ohc=GYUNFC4BYAAAX9oMhzO&_nc_ht=scontent-sea1-1.xx&edm=AL-3X8kEAAAA&oh=00_AfAFIQFJ-2f5pdS3JCATLNucz_9bELNdY3pw81Vb-6qjmg&oe=64243CC4","content":null,"likes":3264766,"comments":34310,"is_business":true,"clean":true,"last_update_time":"2023-03-28T01:34:29.344719","followers":85867252,"max_price":103488,"min_price":102217,"location_name":"New York, New York","location_public":true,"is_video":false,"album":["https://instagram.flhe7-2.fna.fbcdn.net/v/t51.2885-15/307836547_8448224861862030_8581261706437410973_n.jpg?stp=dst-jpg_e35_s1080x1080&_nc_ht=instagram.flhe7-2.fna.fbcdn.net&_nc_cat=106&_nc_ohc=keSG5GMEj5gAX91li9j&edm=AABBvjUBAAAA&ccb=7-5&oh=00_AfAqob1M_gunl7o4wxA9AlKBx-Nn0iMLYIaPOJPqdLhsgQ&oe=64268A0E&_nc_sid=83d603","https://instagram.flhe7-1.fna.fbcdn.net/v/t51.2885-15/307974023_663966602114846_6606730847859627168_n.jpg?stp=dst-jpg_e35_s1080x1080&_nc_ht=instagram.flhe7-1.fna.fbcdn.net&_nc_cat=102&_nc_ohc=uNXry7DkHE4AX-6ffM-&edm=AABBvjUBAAAA&ccb=7-5&oh=00_AfCz4bVvOKOItVbnXCV0TuPagKua1YAHFfXyrNZAjl699Q&oe=642794F8&_nc_sid=83d603"],"location_slug":"new-york-new-york","location_id":"212988663","last_comment_ref":"17943099632464171","album_video":["",""]}},{"date":1664582400000,"post":{"tiktok_post_id":null,"url":"https://www.instagram.com/p/CkK0MLEOXbP","post_user_id":"5a3f8fecedc2956dd5bb6ff0","channel":"instagram","author":"priyankachopra","created_at":"2022-10-26T07:44:07+00:00","title":"Love, peace and prosperity to all. From a heart truly laden with gratitude, I wish you all a Happy Diwali. Sorry I’m a little late but decided to stay in the moment just a little bit longer.. \nॐ नमः शिवाय\nFrom ours to yours.\nLove and light \n🪔🙏🏽❤️\nPS: missed u siddharthchopra89","image_url":"https://scontent-sea1-1.cdninstagram.com/v/t51.29350-15/312718963_434311875562787_9095974323526644792_n.jpg?_nc_cat=106&ccb=1-7&_nc_sid=8ae9d6&_nc_ohc=wXBllO9n5PwAX_dexY_&_nc_ht=scontent-sea1-1.cdninstagram.com&edm=AL-3X8kEAAAA&oh=00_AfCGsaVv7N6RcQQ9ciHpajiLhYvzTewGIa-2tB5hFfSeXQ&oe=6426F63B","avatar":"https://scontent-sea1-1.xx.fbcdn.net/v/t51.2885-15/333394199_575867377919749_6203459700522284722_n.jpg?_nc_cat=1&ccb=1-7&_nc_sid=86c713&_nc_ohc=GYUNFC4BYAAAX9oMhzO&_nc_ht=scontent-sea1-1.xx&edm=AL-3X8kEAAAA&oh=00_AfAFIQFJ-2f5pdS3JCATLNucz_9bELNdY3pw81Vb-6qjmg&oe=64243CC4","content":null,"likes":4295923,"comments":10476,"is_business":true,"clean":true,"last_update_time":"2023-03-25T21:33:31.735031","followers":85825955,"max_price":103437,"min_price":102166,"location_name":"","location_public":false,"is_video":false,"album":["https://instagram.fmex3-2.fna.fbcdn.net/v/t51.2885-15/312718963_434311875562787_9095974323526644792_n.jpg?stp=dst-jpg_e35_p1080x1080&_nc_ht=instagram.fmex3-2.fna.fbcdn.net&_nc_cat=111&_nc_ohc=qyj64u5NK8kAX8-Tlwh&edm=AABBvjUBAAAA&ccb=7-5&oh=00_AfBJbzUafs1l7ww2xsMWZuCo2ABWypWc2y5kjOin1Jmf7A&oe=64244FFD&_nc_sid=83d603","https://instagram.fmex3-3.fna.fbcdn.net/v/t51.2885-15/312823568_591239366126578_7428664468390177362_n.jpg?stp=dst-jpg_e35_p1080x1080&_nc_ht=instagram.fmex3-3.fna.fbcdn.net&_nc_cat=110&_nc_ohc=RlyfERs8hIIAX-Vfael&edm=AABBvjUBAAAA&ccb=7-5&oh=00_AfA6Roz-Hy1wXbNWtBvr3vqAk485_Yc2i_sr114BRpIgFw&oe=642457F0&_nc_sid=83d603","https://instagram.fmex3-1.fna.fbcdn.net/v/t51.2885-15/312707924_889606759089456_9187417254954014673_n.jpg?stp=dst-jpg_e35_p1080x1080&_nc_ht=instagram.fmex3-1.fna.fbcdn.net&_nc_cat=100&_nc_ohc=DFRFukWKphMAX_7WtgG&edm=AABBvjUBAAAA&ccb=7-5&oh=00_AfCieqQ3wxanhbbwyaqg2FLhcms8n4wVrVICSg_PpheHOg&oe=64242A22&_nc_sid=83d603","https://instagram.fmex3-2.fna.fbcdn.net/v/t51.2885-15/312800840_485978593483550_2845249214258366729_n.jpg?stp=dst-jpg_e35_p1080x1080&_nc_ht=instagram.fmex3-2.fna.fbcdn.net&_nc_cat=102&_nc_ohc=ddWmF4Nj6dgAX-od3bi&edm=AABBvjUBAAAA&ccb=7-5&oh=00_AfAFxkE3NK-vv8LqI_xfB_c_dmTVQFG7IfiyWxtUtfGfGg&oe=64239128&_nc_sid=83d603","https://instagram.fmex3-2.fna.fbcdn.net/v/t51.2885-15/312695410_116247057936704_6678646950271798888_n.jpg?stp=dst-jpg_e35_p1080x1080&_nc_ht=instagram.fmex3-2.fna.fbcdn.net&_nc_cat=108&_nc_ohc=xBBY1fL2RRQAX_LIkZJ&edm=AABBvjUBAAAA&ccb=7-5&oh=00_AfBjPlVmjhUGArqEe9NmL3DHUcSzBS64n6mVYjTml5aJ0A&oe=64252F27&_nc_sid=83d603","https://instagram.fmex3-1.fna.fbcdn.net/v/t51.2885-15/312668271_521812893290751_1812625476317689031_n.jpg?stp=dst-jpg_e35_p1080x1080&_nc_ht=instagram.fmex3-1.fna.fbcdn.net&_nc_cat=103&_nc_ohc=0Zwxaz8wH8QAX_RnKD7&edm=AABBvjUBAAAA&ccb=7-5&oh=00_AfCXff82-Px-rKNajY9rMZz5oabWH2gtScRNeozAWXuLeQ&oe=6423AD76&_nc_sid=83d603","https://instagram.fmex3-3.fna.fbcdn.net/v/t51.2885-15/312550649_1802687950123601_1840825209400287886_n.jpg?stp=dst-jpg_e35_p1080x1080&_nc_ht=instagram.fmex3-3.fna.fbcdn.net&_nc_cat=105&_nc_ohc=EY0Nrim-bc8AX-Rfn2u&edm=AABBvjUBAAAA&ccb=7-5&oh=00_AfD8Lwb1z0snupfN7yRnkybQA85vUxcxX-6oUK-myDozIg&oe=642385E9&_nc_sid=83d603","https://instagram.fmex3-2.fna.fbcdn.net/v/t51.2885-15/312664337_411672687664691_8984838507507983668_n.jpg?stp=dst-jpg_e35_p1080x1080&_nc_ht=instagram.fmex3-2.fna.fbcdn.net&_nc_cat=111&_nc_ohc=jN8quLtW_rAAX9lrIbu&edm=AABBvjUBAAAA&ccb=7-5&oh=00_AfBqSyMhwx2TNItzLnGTDwITTfc5cD3RenJIRBkF32sDuQ&oe=6424FE53&_nc_sid=83d603","https://instagram.fmex3-3.fna.fbcdn.net/v/t51.2885-15/305723506_103111839241997_2528844075525809608_n.jpg?stp=dst-jpg_e35_p1080x1080&_nc_ht=instagram.fmex3-3.fna.fbcdn.net&_nc_cat=105&_nc_ohc=5IZNXW9ScbIAX-tc4ub&edm=AABBvjUBAAAA&ccb=7-5&oh=00_AfB_Dhy8ysEUkEgliYqusMX_uhZe6-V_tw6yfthohMG1JQ&oe=6423BE56&_nc_sid=83d603"],"location_slug":"","location_id":"","album_video":["","","","","","","","",""]}},{"date":1667260800000,"post":{"tiktok_post_id":null,"url":"https://www.instagram.com/p/CkxjAY2OIQx","post_user_id":"5a3f8fecedc2956dd5bb6ff0","channel":"instagram","author":"priyankachopra","created_at":"2022-11-10T08:44:20","title":"Home ❤️🙏🏽💫🧿","image_url":"https://s3-us-west-2.amazonaws.com/crawler.img/637049a5d16ad8e3b475df4a.jpg","avatar":"https://scontent-sea1-1.xx.fbcdn.net/v/t51.2885-15/333394199_575867377919749_6203459700522284722_n.jpg?_nc_cat=1&ccb=1-7&_nc_sid=86c713&_nc_ohc=GYUNFC4BYAAAX9oMhzO&_nc_ht=scontent-sea1-1.xx&edm=AL-3X8kEAAAA&oh=00_AfAFIQFJ-2f5pdS3JCATLNucz_9bELNdY3pw81Vb-6qjmg&oe=64243CC4","content":null,"likes":4097391,"comments":8069,"is_business":true,"clean":true,"last_update_time":"2023-03-28T01:25:41.923250","followers":85867252,"max_price":103488,"min_price":102217,"location_name":"Los Angeles, California","location_public":true,"is_video":false,"album":[],"location_slug":"los-angeles-california","location_id":"212999109","id":null,"album_video":[]}},{"date":1669852800000,"post":{"tiktok_post_id":null,"url":"https://www.instagram.com/p/CloFqHZNr1f","post_user_id":"5a3f8fecedc2956dd5bb6ff0","channel":"instagram","author":"priyankachopra","created_at":"2022-12-01T13:06:07","title":"Find yourself a guy that reminds you everyday that you’re loved. Happy anniversary babe. ❤️","image_url":"https://s3-us-west-2.amazonaws.com/crawler.img/6389c8dc852af61d23d0c1e9.jpg","avatar":"https://scontent-sea1-1.xx.fbcdn.net/v/t51.2885-15/333394199_575867377919749_6203459700522284722_n.jpg?_nc_cat=1&ccb=1-7&_nc_sid=86c713&_nc_ohc=GYUNFC4BYAAAX9oMhzO&_nc_ht=scontent-sea1-1.xx&edm=AL-3X8kEAAAA&oh=00_AfAFIQFJ-2f5pdS3JCATLNucz_9bELNdY3pw81Vb-6qjmg&oe=64243CC4","content":null,"likes":2936377,"comments":7559,"is_business":true,"clean":true,"last_update_time":"2023-03-28T01:24:37.305435","followers":85867252,"max_price":103488,"min_price":102217,"location_name":"","location_public":false,"is_video":false,"album":[],"location_slug":"","location_id":"","id":null,"album_video":[]}},{"date":1672531200000,"post":{"tiktok_post_id":null,"url":"https://www.instagram.com/p/CnvPtKuJrgg","post_user_id":"5a3f8fecedc2956dd5bb6ff0","channel":"instagram","author":"priyankachopra","created_at":"2023-01-23T00:51:23","title":"Sunday 😍🙏🏽🤍","image_url":"https://s3-us-west-2.amazonaws.com/crawler.img/63d08e085fa36adc050663b9.jpg","avatar":"https://scontent-sea1-1.xx.fbcdn.net/v/t51.2885-15/333394199_575867377919749_6203459700522284722_n.jpg?_nc_cat=1&ccb=1-7&_nc_sid=86c713&_nc_ohc=GYUNFC4BYAAAX9oMhzO&_nc_ht=scontent-sea1-1.xx&edm=AL-3X8kEAAAA&oh=00_AfAFIQFJ-2f5pdS3JCATLNucz_9bELNdY3pw81Vb-6qjmg&oe=64243CC4","content":null,"likes":3288310,"comments":8083,"is_business":true,"clean":true,"last_update_time":"2023-03-28T01:21:04.091514","followers":85867252,"max_price":103488,"min_price":102217,"location_name":"Malibu, California","location_public":true,"is_video":false,"album":["https://instagram.fmdz1-1.fna.fbcdn.net/v/t51.2885-15/326423045_1424701834602527_3695976375055410200_n.jpg?stp=dst-jpg_e35_p1080x1080&_nc_ht=instagram.fmdz1-1.fna.fbcdn.net&_nc_cat=111&_nc_ohc=srjIJHuUwFMAX_p2Hwp&edm=AABBvjUBAAAA&ccb=7-5&oh=00_AfDinYYByPKJxlKIZsLtJV6SLOxDYW0YtMTlx-HEhsJHdw&oe=64274346&_nc_sid=83d603","https://instagram.fmdz1-1.fna.fbcdn.net/v/t51.2885-15/326308906_130674216557615_7776064246985873219_n.jpg?stp=dst-jpg_e35_p1080x1080&_nc_ht=instagram.fmdz1-1.fna.fbcdn.net&_nc_cat=111&_nc_ohc=9-uXgYMONzoAX96PtTn&edm=AABBvjUBAAAA&ccb=7-5&oh=00_AfBHzAeE_BZPzWoX4maw3fNZpUKGoR7NG-PGr0CShQ8LYA&oe=64263A07&_nc_sid=83d603","https://instagram.fmdz1-1.fna.fbcdn.net/v/t51.2885-15/326715489_183163954328565_3587753184703185608_n.jpg?stp=dst-jpg_e35_p1080x1080&_nc_ht=instagram.fmdz1-1.fna.fbcdn.net&_nc_cat=109&_nc_ohc=9ZEryHcmFvsAX-PgjdE&edm=AABBvjUBAAAA&ccb=7-5&oh=00_AfD-NRPctmJw-j7y4FFiraUD3g6j5_T9gp4EltbeQpekcg&oe=6427F203&_nc_sid=83d603"],"location_slug":"malibu-california","location_id":"213873866","id":null,"album_video":["","",""]}},{"date":1675209600000,"post":{"tiktok_post_id":null,"url":"https://www.instagram.com/p/Co01_gFJYxD","post_user_id":"5a3f8fecedc2956dd5bb6ff0","channel":"instagram","author":"priyankachopra","created_at":"2023-02-19T01:33:32+00:00","title":"Days like this. ❤️","image_url":"https://scontent-sea1-1.cdninstagram.com/v/t51.29350-15/331325270_940079183792306_644158972195797335_n.jpg?_nc_cat=102&ccb=1-7&_nc_sid=8ae9d6&_nc_ohc=yTNqs7FnZJUAX_GRFry&_nc_ht=scontent-sea1-1.cdninstagram.com&edm=AL-3X8kEAAAA&oh=00_AfBdi-68ZGW5ucYE0QOp_SwKhRM7sI44KQEX6PQfU85-lA&oe=64EC262B","avatar":"https://scontent-sea1-1.xx.fbcdn.net/v/t51.2885-15/353912973_1110210083269746_2219558904671761519_n.jpg?_nc_cat=1&ccb=1-7&_nc_sid=7d201b&_nc_ohc=5VOQGZxAXxsAX-4bBxI&_nc_ht=scontent-sea1-1.xx&edm=AL-3X8kEAAAA&oh=00_AfBfx5l0CBe_M_-blruFEIk8vqwrhZStfcI9ipHmzOZdyg&oe=64DDA224","content":null,"likes":4133912,"comments":9753,"is_business":true,"clean":true,"last_update_time":"2023-04-26T11:24:22.524597","followers":86491183,"max_price":103839,"min_price":102569,"location_name":"Las Vegas, Nevada","location_public":true,"is_video":false,"album":["https://instagram.fath4-2.fna.fbcdn.net/v/t51.2885-15/331325270_940079183792306_644158972195797335_n.jpg?stp=dst-jpg_e35_p1080x1080&_nc_ht=instagram.fath4-2.fna.fbcdn.net&_nc_cat=102&_nc_ohc=slS_gA3O8QwAX-0Nfo2&edm=AABBvjUBAAAA&ccb=7-5&oh=00_AfCuZXBnJmN5nnDnZR-ZCSKQwy_CFu4_C6GwgwrSto1vBw&oe=644E0A1A&_nc_sid=83d603","https://instagram.fath4-2.fna.fbcdn.net/v/t51.2885-15/331586517_213457981240717_6221297541214266392_n.jpg?stp=dst-jpg_e35_p1080x1080&_nc_ht=instagram.fath4-2.fna.fbcdn.net&_nc_cat=101&_nc_ohc=9GvHrb4zWtgAX_LL_Hf&edm=AABBvjUBAAAA&ccb=7-5&oh=00_AfC2klRtgFHuVmUEoEmAe85pvX5ImFSNUCB54ueMnXdmNg&oe=644E47A0&_nc_sid=83d603"],"location_slug":"las-vegas-nevada","location_id":"212901056","album_video":["",""],"is_album":true}},{"date":1677628800000,"post":{"tiktok_post_id":null,"url":"https://www.instagram.com/p/CpmNiCZoQSH","post_user_id":"5a3f8fecedc2956dd5bb6ff0","channel":"instagram","author":"priyankachopra","created_at":"2023-03-10T05:42:01+00:00","title":"South Asian Excellence at the Oscars\n\nPhotographer: tylerhenderson \nHair: bridgetbragerhair \nMakeup: missjobaker \nJewellery: bulgari\nStyling: stylebyami \nIn falgunishanepeacockindia","image_url":"https://scontent-sea1-1.cdninstagram.com/v/t51.29350-15/326689553_762703045102075_3797215492461435778_n.jpg?_nc_cat=101&ccb=1-7&_nc_sid=8ae9d6&_nc_ohc=RPUS8VYsj2EAX9UMDhP&_nc_ht=scontent-sea1-1.cdninstagram.com&edm=AL-3X8kEAAAA&oh=00_AfA3KnxrCcgudans10-8Nta5axQL4FIuZG6U3SXugM-oaw&oe=64ECAFB0","avatar":"https://scontent-sea1-1.xx.fbcdn.net/v/t51.2885-15/353912973_1110210083269746_2219558904671761519_n.jpg?_nc_cat=1&ccb=1-7&_nc_sid=7d201b&_nc_ohc=5VOQGZxAXxsAX-4bBxI&_nc_ht=scontent-sea1-1.xx&edm=AL-3X8kEAAAA&oh=00_AfBfx5l0CBe_M_-blruFEIk8vqwrhZStfcI9ipHmzOZdyg&oe=64DDA224","content":null,"likes":2311120,"comments":7791,"is_business":true,"clean":true,"last_update_time":"2023-05-05T08:25:55.974124","followers":86759470,"max_price":104257,"min_price":102989,"location_name":"Los Angeles, California","location_public":true,"is_video":false,"album":["https://scontent-lax3-2.cdninstagram.com/v/t51.2885-15/326689553_762703045102075_3797215492461435778_n.jpg?stp=dst-jpg_e35_p1080x1080&_nc_ht=scontent-lax3-2.cdninstagram.com&_nc_cat=1&_nc_ohc=A26_L0R0-mkAX8DWGPO&edm=AABBvjUBAAAA&ccb=7-5&oh=00_AfDpWu45RAQloOKVJwFj076S0uBnWFnmVOLnxbb3zIdgiA&oe=64599B2A&_nc_sid=83d603","https://scontent-lax3-1.cdninstagram.com/v/t51.2885-15/334681155_746085606955196_3743788633089416733_n.jpg?stp=dst-jpg_e35_p1080x1080&_nc_ht=scontent-lax3-1.cdninstagram.com&_nc_cat=108&_nc_ohc=oEM37hqWT7YAX-eu4Pz&edm=AABBvjUBAAAA&ccb=7-5&oh=00_AfAn0H6DEokdoKzs1BEVIeEosuNJWdRnKgj-MPq_Tam4gQ&oe=64593B88&_nc_sid=83d603","https://scontent-lax3-2.cdninstagram.com/v/t51.2885-15/333193429_598533968823168_7812344913191642761_n.jpg?stp=dst-jpg_e35_p1080x1080&_nc_ht=scontent-lax3-2.cdninstagram.com&_nc_cat=100&_nc_ohc=BLYT-sQcL2MAX8jVLKw&edm=AABBvjUBAAAA&ccb=7-5&oh=00_AfDNaVFxAyURwGNrvL4-amoQm9l_vIJvWFUUNkrWZttkmA&oe=645A464A&_nc_sid=83d603","https://scontent-lax3-1.cdninstagram.com/v/t51.2885-15/334371540_591022715966510_3208006686149289816_n.jpg?stp=dst-jpg_e35_p1080x1080&_nc_ht=scontent-lax3-1.cdninstagram.com&_nc_cat=102&_nc_ohc=ogzJNcd2eYIAX-gfegH&edm=AABBvjUBAAAA&ccb=7-5&oh=00_AfAlI2EuqMe3scpJRF-TIQOu3uAzzN_jBi3xyEf5SM8-FQ&oe=6458E46E&_nc_sid=83d603","https://scontent-lax3-2.cdninstagram.com/v/t51.2885-15/334207245_212380104667955_6877600807951184373_n.jpg?stp=dst-jpg_e35_p1080x1080&_nc_ht=scontent-lax3-2.cdninstagram.com&_nc_cat=111&_nc_ohc=OXrfpQSOsPsAX8snDg5&edm=AABBvjUBAAAA&ccb=7-5&oh=00_AfDPbaWSBUyuFpASTOtJbrwJzqz6ELPT1SA4i4yoeLox5A&oe=645A545A&_nc_sid=83d603"],"location_slug":"los-angeles-california","location_id":"212999109","album_video":["","","","",""],"is_album":true}},{"date":1680307200000,"post":{"tiktok_post_id":null,"url":"https://www.instagram.com/p/CqiDOdrD8nw","post_user_id":"5a3f8fecedc2956dd5bb6ff0","channel":"instagram","author":"priyankachopra","created_at":"2023-04-02T11:26:23+00:00","title":"Date night and a 🛺….. \nwith my forever guy nickjonas \n\nThank you stylebyami as always for your amazing collaboration. I knew I wanted to wear an upcycled vintage look with a modern twist! So my outfit was an amalgamation of the east and the west! Like me! \n\nThank you amitaggarwalofficial for coming through and creating this handcrafted beauty with a story that is so apt for an evening celebrating Indian art and Fashion. \n\nThis beautiful outfit was created using a 65 year old vintage Banarasi patola (Brocade)saree with silver threads and a gold electroplating on khadi silk. It is paired with a sequins sheet holographic bustier to reflect the nine colours of ikat weave that the brocade is set in.\n\nThank you for your genius Amit and your gifted team.\n\nCongratulations #NitaAmbani and _iiishmagish for creating an incredible exhibition of the history Indian fashion at the nmacc.india! So proud of this exquisite space and the potential it has to promote Indian Art and design ❤️\n\nPs- Also for all wondering auto uncle took the cake! Was lovely and gracious! Thank you auto uncle!","image_url":"https://scontent-sea1-1.cdninstagram.com/v/t51.29350-15/339151492_876234766779373_5039983966128343713_n.jpg?_nc_cat=101&ccb=1-7&_nc_sid=18de74&_nc_eui2=AeGcuBGHV3_Qs43yJg1-Q0HE6TB53kBZUnHpMHneQFlScZ-atg3a1n6P-OS-hSdEKqU&_nc_ohc=oz2QS5mACl4AX9yeysd&_nc_ht=scontent-sea1-1.cdninstagram.com&edm=AL-3X8kEAAAA&oh=00_AfAyis8bqvjaVL2SfhfSc-1bKVTTfw032768wFCQlbKaEg&oe=65BCAD89","avatar":"https://scontent-sea1-1.xx.fbcdn.net/v/t51.2885-15/384293351_1081650986155780_5846010834968574051_n.jpg?_nc_cat=1&ccb=1-7&_nc_sid=7d201b&_nc_ohc=wcFNK1UeLGUAX_aGUHg&_nc_ht=scontent-sea1-1.xx&edm=AL-3X8kEAAAA&oh=00_AfCDRwRScJgyhwJdVghF2Jzj_xkc3RojqnmIz17IZluk3g&oe=65B70F72","content":null,"likes":5566430,"comments":18779,"is_business":true,"clean":true,"last_update_time":"2023-05-31T16:03:43.246261","followers":87515142,"max_price":105179,"min_price":103914,"location_name":"Mumbai, Maharashtra","location_public":true,"is_video":false,"album":["https://instagram.flhe5-1.fna.fbcdn.net/v/t51.2885-15/339151492_876234766779373_5039983966128343713_n.jpg?stp=dst-jpg_e35_p1080x1080&_nc_ht=instagram.flhe5-1.fna.fbcdn.net&_nc_cat=101&_nc_ohc=VWfVFbvCkMsAX_o8fQl&edm=AABBvjUBAAAA&ccb=7-5&oh=00_AfBBo3bzmG1FhDtbo2geWhtMqQXRIZEAzU_UGbdaCWxInw&oe=647CB4CF&_nc_sid=62388f","https://instagram.flhe5-1.fna.fbcdn.net/v/t51.2885-15/338749271_800933094928553_1437859098528027019_n.jpg?stp=dst-jpg_e35_p1080x1080&_nc_ht=instagram.flhe5-1.fna.fbcdn.net&_nc_cat=105&_nc_ohc=pZ-QP1u8TPAAX9zw4wD&edm=AABBvjUBAAAA&ccb=7-5&oh=00_AfB5Jh-khT1eXMMr8ZbaDzW9adZW4Me9fewXpTH3Dsx_Cg&oe=647BD08F&_nc_sid=62388f","https://instagram.flhe5-1.fna.fbcdn.net/v/t51.2885-15/338846286_168696979371385_4871415279387207600_n.jpg?stp=dst-jpg_e35_p1080x1080&_nc_ht=instagram.flhe5-1.fna.fbcdn.net&_nc_cat=101&_nc_ohc=qNGrlTkD_CQAX9xnWvC&edm=AABBvjUBAAAA&ccb=7-5&oh=00_AfB6tYidsR92R_kYyYO1hxkz6NCxJKqQNxg1Hq8w3Xk9zQ&oe=647CB491&_nc_sid=62388f","https://instagram.flhe5-1.fna.fbcdn.net/v/t51.2885-15/339105426_745366083744065_5546119508930499037_n.jpg?stp=dst-jpg_e35_p1080x1080&_nc_ht=instagram.flhe5-1.fna.fbcdn.net&_nc_cat=105&_nc_ohc=cKfb51NJvyAAX-_mcci&edm=AABBvjUBAAAA&ccb=7-5&oh=00_AfD72hKwt6cxMKIa398_la3Tkldhcnk_xwsdSJwmozcf_Q&oe=647B91C6&_nc_sid=62388f","https://instagram.flhe5-1.fna.fbcdn.net/v/t51.2885-15/338781587_188613543943590_6389333839335068125_n.jpg?stp=dst-jpg_e35_p1080x1080&_nc_ht=instagram.flhe5-1.fna.fbcdn.net&_nc_cat=106&_nc_ohc=dTRP9PA2gnwAX_0_vEb&edm=AABBvjUBAAAA&ccb=7-5&oh=00_AfDaoc1g5Ho2fGtW1Stn7v90WcICBjNT6oalv1mhfkcPPw&oe=647C122D&_nc_sid=62388f"],"album_video":["","","","",""],"location_slug":"mumbai-maharashtra","location_id":"216978098","is_album":true}},{"date":1682899200000,"post":{"tiktok_post_id":null,"url":"https://www.instagram.com/p/CsYFhzNofRM","post_user_id":"5a3f8fecedc2956dd5bb6ff0","channel":"instagram","author":"priyankachopra","created_at":"2023-05-18T07:36:53+00:00","title":"La vita è bella… with bulgari in Venice for the reveal of the new #BulgariMediterranea High Jewellery Collection. \n\nThank you lucia_silvestri and jc.babin for having me!\nbulgari #Bulgari #BulgariHighJewelry","image_url":"https://scontent-sea1-1.cdninstagram.com/v/t51.29350-15/347201259_927919435126155_9166915101938825646_n.jpg?_nc_cat=107&ccb=1-7&_nc_sid=18de74&_nc_ohc=JcWDLIAz_AwAX_OLyrt&_nc_ht=scontent-sea1-1.cdninstagram.com&edm=AL-3X8kEAAAA&oh=00_AfDfZD0KYeblvhuyiVRWj-bY3HWotgAgtz2p5-E0p6fMsA&oe=65D3A7AE","avatar":"https://scontent-sea1-1.xx.fbcdn.net/v/t51.2885-15/384293351_1081650986155780_5846010834968574051_n.jpg?_nc_cat=1&ccb=1-7&_nc_sid=7d201b&_nc_ohc=lzAUCcgDoSIAX81uLoW&_nc_ht=scontent-sea1-1.xx&edm=AL-3X8kEAAAA&oh=00_AfBCF9k9sgeo7Jgem5mtJ54h2CITBxPNwVi2NskMTWzb8g&oe=65D0C4B2","content":null,"is_album":true,"likes":3451206,"comments":13868,"is_business":true,"album_video":["","","",""],"album":["https://scontent-sea1-1.cdninstagram.com/v/t51.29350-15/347201259_927919435126155_9166915101938825646_n.jpg?_nc_cat=107&ccb=1-7&_nc_sid=c4dd86&_nc_ohc=Uyk55B9yTXoAX_D86ic&_nc_ht=scontent-sea1-1.cdninstagram.com&edm=AL-3X8kEAAAA&oh=00_AfAcFhT_ry-vkv63ehY_pYllyIVfnm21jM17HL0cwB73ng&oe=659A4E6E","https://scontent-sea1-1.cdninstagram.com/v/t51.29350-15/347095772_1369604703605126_9037655751702594829_n.jpg?_nc_cat=101&ccb=1-7&_nc_sid=c4dd86&_nc_ohc=MRAVWQJ4cR4AX93Wai-&_nc_ht=scontent-sea1-1.cdninstagram.com&edm=AL-3X8kEAAAA&oh=00_AfBQLNXtuLI7hT_MMH4-p3Abt89H5YlbeCtcDRsIHiK_WA&oe=659A1597","https://scontent-sea1-1.cdninstagram.com/v/t51.29350-15/347421949_1296978237916466_8350605205227730509_n.jpg?_nc_cat=106&ccb=1-7&_nc_sid=c4dd86&_nc_ohc=-W53FsijQ8kAX8G--Sz&_nc_ht=scontent-sea1-1.cdninstagram.com&edm=AL-3X8kEAAAA&oh=00_AfCVVH2QgFGY-63cHaLolN6EbqIcPNVgZdMowZDJ4Ct4VQ&oe=6599EB3F","https://scontent-sea1-1.cdninstagram.com/v/t51.29350-15/347288150_920962342291642_6084718341559857531_n.jpg?_nc_cat=102&ccb=1-7&_nc_sid=c4dd86&_nc_ohc=8Cy6xnUeM9cAX-6dg9R&_nc_oc=AQmDRgAJL7oOJJzfPhRHZtPgScRvRa00f9d6qoW9UUFFZmBxD8PDHF_QsImrUq6HVd0&_nc_ht=scontent-sea1-1.cdninstagram.com&edm=AL-3X8kEAAAA&oh=00_AfDA4pekkDv5hVey9W28EtKi575POkzXuS39wgNARWI-yg&oe=65997F4D"],"clean":true,"last_update_time":"2024-01-01T12:19:39.639353","followers":90262604,"max_price":108621,"min_price":107366,"location_name":"","location_public":false,"is_video":false,"location_slug":"","location_id":"","id":null}},{"date":1685577600000,"post":{"tiktok_post_id":null,"url":"https://www.instagram.com/p/CtpRNuZto-2","post_user_id":"5a3f8fecedc2956dd5bb6ff0","channel":"instagram","author":"priyankachopra","created_at":"2023-06-18T20:17:29+00:00","title":"He is your biggest champion.. He’ll be the loudest in the room when you win. His wisdom will be the shoulders you stand on. Your tears will break his heart. He will never show you he’s hurting. His joy is your joy. He is dada or dad or papa or whatever you call them. \n\nI love you nickjonas thank you for being ours. MM and I are so lucky. \nLove you papakjonas you were so special today and everyday ❤️\nHappy Father’s Day. Give them a hug if you can. Miss you papa.","image_url":"https://scontent-sea1-1.cdninstagram.com/v/t51.29350-15/354450015_802456934539693_8815598086117988357_n.jpg?_nc_cat=103&ccb=1-7&_nc_sid=18de74&_nc_ohc=BpCtAG4sM3gAX_dn98a&_nc_ht=scontent-sea1-1.cdninstagram.com&edm=AL-3X8kEAAAA&oh=00_AfBvL-boIG9-yTcUE3khi_A61jN57jRVD_G32UEyuzCROg&oe=65D4926C","avatar":"https://scontent-sea1-1.xx.fbcdn.net/v/t51.2885-15/384293351_1081650986155780_5846010834968574051_n.jpg?_nc_cat=1&ccb=1-7&_nc_sid=7d201b&_nc_ohc=lzAUCcgDoSIAX81uLoW&_nc_ht=scontent-sea1-1.xx&edm=AL-3X8kEAAAA&oh=00_AfBCF9k9sgeo7Jgem5mtJ54h2CITBxPNwVi2NskMTWzb8g&oe=65D0C4B2","content":null,"is_album":true,"likes":2779647,"comments":3528,"is_business":true,"album_video":["","",""],"album":["https://instagram.faqp1-1.fna.fbcdn.net/v/t51.2885-15/354450015_802456934539693_8815598086117988357_n.jpg?stp=dst-jpg_e35_s1080x1080&_nc_ht=instagram.faqp1-1.fna.fbcdn.net&_nc_cat=101&_nc_ohc=rGDZAiQwVJYAX8MhyTs&edm=AABBvjUBAAAA&ccb=7-5&oh=00_AfBB0xPsoXqbeJiiNgr8OGJWGIQW5O8Rb7iQLpSorfPrpQ&oe=65CFE26E&_nc_sid=4f4799","https://instagram.faqp1-1.fna.fbcdn.net/v/t51.2885-15/354390269_2028699124129804_7321405906571614004_n.jpg?stp=dst-jpg_e35_s1080x1080&_nc_ht=instagram.faqp1-1.fna.fbcdn.net&_nc_cat=104&_nc_ohc=uKLku52jFksAX8cC8VV&edm=AABBvjUBAAAA&ccb=7-5&oh=00_AfC-bhZTA3fB61MjSj4Tav-om6dzTWur9ukpnpTx1KywcQ&oe=65D027A2&_nc_sid=4f4799","https://instagram.faqp1-1.fna.fbcdn.net/v/t51.2885-15/354402328_953595592544107_8020174822679957361_n.jpg?stp=dst-jpg_e35&_nc_ht=instagram.faqp1-1.fna.fbcdn.net&_nc_cat=107&_nc_ohc=-IkQ4hTbFSYAX99DWHG&edm=AABBvjUBAAAA&ccb=7-5&oh=00_AfAJw0ZdLRdjgwCDNOkAg60vASIXMmRCoMP9__cVYxhDJA&oe=65D03A2F&_nc_sid=4f4799"],"clean":true,"last_update_time":"2024-02-13T19:11:53.642742","followers":90582979,"max_price":108894,"min_price":107639,"location_name":"London, United Kingdom","location_public":true,"is_video":false,"location_slug":"london-united-kingdom","location_id":"213385402","id":null}},{"date":1688169600000,"post":{"tiktok_post_id":null,"url":"https://www.instagram.com/reel/CuutQMtpkHu","post_user_id":"5a3f8fecedc2956dd5bb6ff0","channel":"instagram","author":"priyankachopra","created_at":"2023-07-15T19:34:26+00:00","title":"Ponytails are complicated","image_url":"https://scontent-sea1-1.cdninstagram.com/o1/v/t16/f1/m82/E2431E565D3D28428B486C4D30B34DA9_video_dashinit.mp4?efg=eyJ2ZW5jb2RlX3RhZyI6InZ0c192b2RfdXJsZ2VuLmNsaXBzLnVua25vd24tQzMuNzIwLmRhc2hfYmFzZWxpbmVfMV92MSJ9&_nc_ht=scontent-sea1-1.cdninstagram.com&_nc_cat=100&vs=246286858199556_3033021226&_nc_vs=HBksFQIYT2lnX3hwdl9yZWVsc19wZXJtYW5lbnRfcHJvZC9FMjQzMUU1NjVEM0QyODQyOEI0ODZDNEQzMEIzNERBOV92aWRlb19kYXNoaW5pdC5tcDQVAALIAQAVAhg6cGFzc3Rocm91Z2hfZXZlcnN0b3JlL0dBVl9oUlZaQkpTcnV3OERBRGsxNlYwQl9HeGpicV9FQUFBRhUCAsgBACgAGAAbAYgHdXNlX29pbAExFQAAJtSy1fay94VAFQIoAkMzLBdARPqfvnbItBgSZGFzaF9iYXNlbGluZV8xX3YxEQB1AAA%3D&ccb=9-4&oh=00_AfAvyOZ9OWFrntQWIJ_DrIWn1IPZ5v7DXWI4rrxsIRnX3g&oe=65D0A1FF&_nc_sid=1d576d&_nc_rid=2b0a6e6f40","avatar":"https://scontent-sea1-1.xx.fbcdn.net/v/t51.2885-15/384293351_1081650986155780_5846010834968574051_n.jpg?_nc_cat=1&ccb=1-7&_nc_sid=7d201b&_nc_ohc=lzAUCcgDoSIAX81uLoW&_nc_ht=scontent-sea1-1.xx&edm=AL-3X8kEAAAA&oh=00_AfBCF9k9sgeo7Jgem5mtJ54h2CITBxPNwVi2NskMTWzb8g&oe=65D0C4B2","content":null,"likes":1126536,"comments":5884,"is_video":true,"is_business":true,"clean":true,"last_update_time":"2024-02-13T19:11:07.144278","followers":90582979,"max_price":108894,"min_price":107639,"location_name":"London, United Kingdom","location_public":true,"video_url":"https://instagram.fcpv2-2.fna.fbcdn.net/o1/v/t16/f1/m82/E2431E565D3D28428B486C4D30B34DA9_video_dashinit.mp4?efg=eyJxZV9ncm91cHMiOiJbXCJpZ193ZWJfZGVsaXZlcnlfdnRzX290ZlwiXSIsInZlbmNvZGVfdGFnIjoidnRzX3ZvZF91cmxnZW4uY2xpcHMuYzIuNzIwLmJhc2VsaW5lIn0&_nc_ht=instagram.fcpv2-2.fna.fbcdn.net&_nc_cat=100&vs=246286858199556_2954227767&_nc_vs=HBksFQIYT2lnX3hwdl9yZWVsc19wZXJtYW5lbnRfcHJvZC9FMjQzMUU1NjVEM0QyODQyOEI0ODZDNEQzMEIzNERBOV92aWRlb19kYXNoaW5pdC5tcDQVAALIAQAVAhg6cGFzc3Rocm91Z2hfZXZlcnN0b3JlL0dBVl9oUlZaQkpTcnV3OERBRGsxNlYwQl9HeGpicV9FQUFBRhUCAsgBACgAGAAbABUAACbUstX2sveFQBUCKAJDMywXQET7peNT988YEmRhc2hfYmFzZWxpbmVfMV92MREAdf4HAA%3D%3D&_nc_rid=6179113f81&ccb=9-4&oh=00_AfAMqxrbts0Gc41EyruMBb7lVoClDMPEzekYI_212OTyFg&oe=65CD563F&_nc_sid=4f4799","album":[],"album_video":[],"location_slug":"london-united-kingdom","views":13095812,"location_id":"213385402"}},{"date":1690848000000,"post":{"tiktok_post_id":null,"url":"https://www.instagram.com/p/Cv5LhIdJ7ae","post_user_id":"5a3f8fecedc2956dd5bb6ff0","channel":"instagram","author":"priyankachopra","created_at":"2023-08-13T17:38:21+00:00","title":"You are a magnet nickjonas MM and I are so lucky to have you❤️ Congratulations on the start of an incredible tour. You’re all in for a huge ride! Let’s gooooo! Great job JB team the Band, the crew. The show was seamless and awe inspiring. Round 2 tonight! ❤️🙏🏽👏💪🏽\n\n📸 : nicolasgerardin","image_url":"https://scontent-sea1-1.cdninstagram.com/v/t51.29350-15/367365512_257000747127808_4110670548707426034_n.jpg?_nc_cat=102&ccb=1-7&_nc_sid=18de74&_nc_ohc=fRcNJLjWeyMAX-H88NB&_nc_ht=scontent-sea1-1.cdninstagram.com&edm=AL-3X8kEAAAA&oh=00_AfCqRKwmi4VPzYJA1YqbcvsHexQXeCZyzhldzXWp2om6HA&oe=65D3209D","avatar":"https://scontent-sea1-1.xx.fbcdn.net/v/t51.2885-15/384293351_1081650986155780_5846010834968574051_n.jpg?_nc_cat=1&ccb=1-7&_nc_sid=7d201b&_nc_ohc=lzAUCcgDoSIAX81uLoW&_nc_ht=scontent-sea1-1.xx&edm=AL-3X8kEAAAA&oh=00_AfBCF9k9sgeo7Jgem5mtJ54h2CITBxPNwVi2NskMTWzb8g&oe=65D0C4B2","content":null,"likes":2728188,"comments":4797,"is_business":true,"clean":true,"album":["https://scontent-tir3-1.cdninstagram.com/v/t39.30808-6/367440055_18400425724041483_2090050116146884959_n.jpg?stp=dst-jpg_e35_p1080x1080_sh0.08&_nc_ht=scontent-tir3-1.cdninstagram.com&_nc_cat=103&_nc_ohc=2W1T_1tH0TAAX-YqWV9&edm=AABBvjUAAAAA&ccb=7-5&oh=00_AfBy3wQM89LHQpYyqWJIVh8a8q5rO6Wcd7Hu5QqMDMq98Q&oe=65D1371E&_nc_sid=4f4799","https://scontent-tir3-1.cdninstagram.com/v/t39.30808-6/366908541_18400425733041483_7920798597195964282_n.jpg?stp=dst-jpg_e35_p1080x1080_sh0.08&_nc_ht=scontent-tir3-1.cdninstagram.com&_nc_cat=103&_nc_ohc=jO4W2bmdOGgAX_MIJtI&edm=AABBvjUAAAAA&ccb=7-5&oh=00_AfDz6QRwYAeQwUbsqGoysbD0j8iHLwZqjrFWVTehmg-zuw&oe=65D01C26&_nc_sid=4f4799","https://scontent-tir3-1.cdninstagram.com/v/t39.30808-6/366910791_18400425742041483_6267228772309079646_n.jpg?stp=dst-jpg_e35_p1080x1080_sh0.08&_nc_ht=scontent-tir3-1.cdninstagram.com&_nc_cat=103&_nc_ohc=blHxR-LXejcAX_4Cxyr&edm=AABBvjUAAAAA&ccb=7-5&oh=00_AfBhF4lf1bfBmgngpORUYE_XMnDM_zCURRYSdK2Wadc1Gw&oe=65D06567&_nc_sid=4f4799","https://scontent-tir3-1.cdninstagram.com/v/t39.30808-6/366808372_18400425751041483_2244481637379760729_n.jpg?stp=dst-jpg_e35_p1080x1080_sh0.08&_nc_ht=scontent-tir3-1.cdninstagram.com&_nc_cat=103&_nc_ohc=42N_XMao4z4AX8xzYU3&edm=AABBvjUAAAAA&ccb=7-5&oh=00_AfBbXbYlTpjjkuor_JY5wdfFTLDsv1v35C_U-3JNYffl2Q&oe=65D0C151&_nc_sid=4f4799","https://scontent-tir3-1.cdninstagram.com/v/t39.30808-6/365945563_18400425760041483_8781368193675914932_n.jpg?stp=dst-jpg_e35_p1080x1080_sh0.08&_nc_ht=scontent-tir3-1.cdninstagram.com&_nc_cat=103&_nc_ohc=jukRyWL5CDcAX9aAFZ9&edm=AABBvjUAAAAA&ccb=7-5&oh=00_AfCshZqDaZo3oA8DC-DCrJSWKWds5aAszIfnV6TaNyKToA&oe=65D0E021&_nc_sid=4f4799","https://scontent-tir3-1.cdninstagram.com/v/t39.30808-6/365906523_18400425769041483_4230989806617165553_n.jpg?stp=dst-jpg_e35_p1080x1080_sh0.08&_nc_ht=scontent-tir3-1.cdninstagram.com&_nc_cat=103&_nc_ohc=eiEWhDBfP9cAX-xS8L5&edm=AABBvjUAAAAA&ccb=7-5&oh=00_AfDmItH09iOYK9qg-WKiUu1c7p2oSAZArBtKclXGWh3Wdw&oe=65D080C9&_nc_sid=4f4799"],"is_album":true,"album_video":["","","","","",""],"last_update_time":"2024-02-13T19:10:18.799369","followers":90582979,"max_price":108894,"min_price":107639,"location_name":"Yankee Stadium","location_public":true,"is_video":false,"location_slug":"yankee-stadium","location_id":"1030079727081620","id":null}},{"date":1693526400000,"post":{"tiktok_post_id":null,"url":"https://www.instagram.com/p/Cxm8kNmoojG","post_user_id":"5a3f8fecedc2956dd5bb6ff0","channel":"instagram","author":"priyankachopra","created_at":"2023-09-25T08:44:09+00:00","title":"Picture perfect.. sending so much love to the newly weds on their special day! Welcome to the Chopra family raghavchadha88 … hope you’re ready to dive into the crazy with us 😉🤪❤️\n\nTisha you are the most beautiful bride ever.. we’re sending you and Raghav all the love and blessings for a lifetime of happiness. Take care of each other and protect this beautiful love.\n\nLove you little one. \nparineetichopra","image_url":"https://scontent-sea1-1.cdninstagram.com/v/t51.29350-15/383476186_276842918574391_4868683194397552459_n.jpg?_nc_cat=102&ccb=1-7&_nc_sid=18de74&_nc_ohc=Rukf22l2REMAX-9RF1y&_nc_ht=scontent-sea1-1.cdninstagram.com&edm=AL-3X8kEAAAA&oh=00_AfAXrnOcWLqMCSKR33VumTRdB2y9iesW26pgbdDaFl5Gwg&oe=65DD6627","avatar":"https://scontent-sea1-1.xx.fbcdn.net/v/t51.2885-15/384293351_1081650986155780_5846010834968574051_n.jpg?_nc_cat=1&ccb=1-7&_nc_sid=7d201b&_nc_ohc=_0HPU6BhDnAAX8s-00_&_nc_ht=scontent-sea1-1.xx&edm=AL-3X8kEAAAA&oh=00_AfAYdcp-9p9kyuK3hMBfq_zxTX1lNuXZToYx96U5RT53xg&oe=65DCA232","content":null,"is_album":true,"likes":4739523,"comments":6440,"is_business":true,"album_video":["","",""],"album":["https://scontent-den2-1.cdninstagram.com/v/t39.30808-6/380284196_18408533482041483_807990942812284516_n.jpg?stp=dst-jpg_e35_p1080x1080_sh0.08&_nc_ht=scontent-den2-1.cdninstagram.com&_nc_cat=103&_nc_ohc=UutKWdDaAgcAX9yxExO&edm=AABBvjUAAAAA&ccb=7-5&oh=00_AfAUovCLWsunRae5L9hqdYtDseQInrVuEDPK3OGEMD9N1w&oe=65DAD356&_nc_sid=4f4799","https://scontent-den2-1.cdninstagram.com/v/t39.30808-6/382173422_18408533494041483_2779527789433538147_n.jpg?stp=dst-jpg_e35_p1080x1080_sh0.08&_nc_ht=scontent-den2-1.cdninstagram.com&_nc_cat=103&_nc_ohc=cDmggfXpw_4AX_9Vh16&edm=AABBvjUAAAAA&ccb=7-5&oh=00_AfDxjxP1FspC-fqtvTeSLdn2-v49MG-KZBjsPuL8rHyRzQ&oe=65DB6004&_nc_sid=4f4799","https://scontent-den2-1.cdninstagram.com/v/t39.30808-6/382700430_18408533503041483_1416962755471145176_n.jpg?stp=dst-jpg_e35_p1080x1080_sh0.08&_nc_ht=scontent-den2-1.cdninstagram.com&_nc_cat=103&_nc_ohc=Ii7vZvT8WSMAX84ACob&edm=AABBvjUAAAAA&ccb=7-5&oh=00_AfBEB5t2dPSnyua7GlNNVVyhroBibXdUd_MsCOnUds-LAg&oe=65DBF65B&_nc_sid=4f4799"],"clean":true,"last_update_time":"2024-02-21T19:22:24.148513","followers":90605650,"max_price":109009,"min_price":107755,"location_name":"","location_public":false,"is_video":false,"location_slug":"","location_id":"","id":null}},{"date":1696118400000,"post":{"tiktok_post_id":null,"url":"https://www.instagram.com/p/Cy6BI52rttZ","post_user_id":"5a3f8fecedc2956dd5bb6ff0","channel":"instagram","author":"priyankachopra","created_at":"2023-10-27T15:01:05+00:00","title":"Opening night ❤️🙏🏽 \nJio Mami Mumbai Film Festival mumbaifilmfestival","image_url":"https://scontent-sea1-1.cdninstagram.com/v/t39.30808-6/395279780_18414507106041483_3767148800968250356_n.jpg?_nc_cat=1&ccb=1-7&_nc_sid=18de74&_nc_ohc=9v-pQCGunKUAX9wjjBB&_nc_ht=scontent-sea1-1.cdninstagram.com&edm=AL-3X8kEAAAA&oh=00_AfBlPI2eRH6__CFVOHKOZcOLf9n-3MXSJ6uC2WdrkhjdCg&oe=65FAC4E5","avatar":"https://scontent-sea1-1.xx.fbcdn.net/v/t51.2885-15/384293351_1081650986155780_5846010834968574051_n.jpg?_nc_cat=1&ccb=1-7&_nc_sid=7d201b&_nc_ohc=7Yntjm8yrmQAX87M20s&_nc_ht=scontent-sea1-1.xx&edm=AL-3X8kEAAAA&oh=00_AfD-Z-lXmkPY9B9TtxhQc7ho-j2X6k0aqroEApAmxhi__A&oe=65F45D32","content":null,"is_album":true,"likes":1016501,"comments":6069,"is_business":true,"album_video":["","","","",""],"album":["https://z-p42-instagram.fadb6-2.fna.fbcdn.net/v/t39.30808-6/395279780_18414507106041483_3767148800968250356_n.jpg?stp=dst-jpg_e35_p1080x1080_sh0.08&_nc_ad=z-m&_nc_ht=z-p42-instagram.fadb6-2.fna.fbcdn.net&_nc_cat=103&_nc_ohc=gWFym1WxiJMAX8mFyA_&edm=AABBvjUAAAAA&ccb=7-5&oh=00_AfC7Xu1mru4BQS_jLRQ8AE2BgYlWODhLhZ5bAAahtzhRaw&oe=65F0E1A5&_nc_sid=4f4799","https://z-p42-instagram.fadb6-2.fna.fbcdn.net/v/t39.30808-6/395376905_18414507115041483_8141633793666676408_n.jpg?stp=dst-jpg_e35_p1080x1080_sh0.08&_nc_ad=z-m&_nc_ht=z-p42-instagram.fadb6-2.fna.fbcdn.net&_nc_cat=103&_nc_ohc=Fbyr423mTWoAX88gA8M&edm=AABBvjUAAAAA&ccb=7-5&oh=00_AfDt1SfE9YvGPKyy1qOMMCAueNhUjgxRmtSRYk72GNUWRQ&oe=65F1598B&_nc_sid=4f4799","https://z-p42-instagram.fadb6-2.fna.fbcdn.net/v/t39.30808-6/395283639_18414507124041483_3521859731119438449_n.jpg?stp=dst-jpg_e35_p1080x1080_sh0.08&_nc_ad=z-m&_nc_ht=z-p42-instagram.fadb6-2.fna.fbcdn.net&_nc_cat=103&_nc_ohc=_y9iF4jKsycAX8nbpg0&edm=AABBvjUAAAAA&ccb=7-5&oh=00_AfCtI69vgjuLVhHSvebf_3Js8H0HJs0d_BSadSPm5Pmeeg&oe=65F19110&_nc_sid=4f4799","https://z-p42-instagram.fadb6-2.fna.fbcdn.net/v/t39.30808-6/395196773_18414507136041483_8451947752359741467_n.jpg?stp=dst-jpg_e35_p1080x1080_sh0.08&_nc_ad=z-m&_nc_ht=z-p42-instagram.fadb6-2.fna.fbcdn.net&_nc_cat=103&_nc_ohc=72BF3r06vpgAX9zQGlP&edm=AABBvjUAAAAA&ccb=7-5&oh=00_AfDqEUmFeCNO0cXHEWSyFKI6oA9gn5rSaKZ2EUAVmnosLw&oe=65F223EF&_nc_sid=4f4799","https://z-p42-instagram.fadb6-2.fna.fbcdn.net/v/t39.30808-6/395280588_18414507145041483_4579749934492279278_n.jpg?stp=dst-jpg_e35_p1080x1080_sh0.08&_nc_ad=z-m&_nc_ht=z-p42-instagram.fadb6-2.fna.fbcdn.net&_nc_cat=103&_nc_ohc=EUvuA2FSF3cAX-d2jaX&edm=AABBvjUAAAAA&ccb=7-5&oh=00_AfC6GKQ3_LQ6yC62-idfjiTfStVd_BqVdR0rYmpzmdkUWw&oe=65F1A568&_nc_sid=4f4799"],"clean":true,"last_update_time":"2024-03-09T19:59:42.323674","followers":90697662,"max_price":109106,"min_price":107852,"location_name":"","location_public":false,"is_video":false,"location_slug":"","location_id":"","id":null}},{"date":1698796800000,"post":{"tiktok_post_id":null,"url":"https://www.instagram.com/reel/C0M1mjGLSGt","post_user_id":"5a3f8fecedc2956dd5bb6ff0","channel":"instagram","author":"priyankachopra","created_at":"2023-11-28T18:59:31+00:00","title":"Pit stop in Abu Dhabi for the F1 🏎️\nvisitabudhabi #AbuDhabiGP\n\n#ad","image_url":null,"avatar":"https://scontent-sea1-1.xx.fbcdn.net/v/t51.2885-15/384293351_1081650986155780_5846010834968574051_n.jpg?_nc_cat=1&ccb=1-7&_nc_sid=7d201b&_nc_ohc=h5XIkVNDwZcAX9WKlPm&_nc_ht=scontent-sea1-1.xx&edm=AL-3X8kEAAAA&oh=00_AfC4i-wcCduMRiZowfLg2Kr3sbEV1RZDECuWgYvYPQMfIA&oe=66042F32","content":null,"likes":1253877,"comments":3831,"is_video":true,"is_business":true,"clean":true,"sponsor":"visitabudhabi","last_update_time":"2024-03-28T05:56:10.916736","brands":["#abudhabigp","#ad","@visitabudhabi"],"followers":90801455,"max_price":109196,"min_price":107942,"sponsored":true,"location_name":"","location_public":false,"video_url":"https://instagram.fknu1-6.fna.fbcdn.net/o1/v/t16/f1/m82/4643F4EAC5E819363C95A325199B7C83_video_dashinit.mp4?efg=eyJxZV9ncm91cHMiOiJbXCJpZ193ZWJfZGVsaXZlcnlfdnRzX290ZlwiXSIsInZlbmNvZGVfdGFnIjoidnRzX3ZvZF91cmxnZW4uY2xpcHMuYzIuNzIwLmJhc2VsaW5lIn0&_nc_ht=instagram.fknu1-6.fna.fbcdn.net&_nc_cat=103&vs=1540099846749260_1280105349&_nc_vs=HBksFQIYT2lnX3hwdl9yZWVsc19wZXJtYW5lbnRfcHJvZC80NjQzRjRFQUM1RTgxOTM2M0M5NUEzMjUxOTlCN0M4M192aWRlb19kYXNoaW5pdC5tcDQVAALIAQAVAhg6cGFzc3Rocm91Z2hfZXZlcnN0b3JlL0dJbHdNUmhJSFpWejFNWUFBUDd1d2ZOXzBoaE1icV9FQUFBRhUCAsgBACgAGAAbABUAACaGlbmC4NCFQBUCKAJDMywXQC%2FXCj1wo9cYEmRhc2hfYmFzZWxpbmVfMV92MREAdf4HAA%3D%3D&_nc_rid=5fbded0dae&ccb=9-4&oh=00_AfAkEYR8K6DsbEm5qawwYC2HC_u8WrdHeXz3-ZUvB3kjBg&oe=6606CA89&_nc_sid=4f4799","album":[],"album_video":[],"location_slug":"","views":8232845,"location_id":""}},{"date":1701388800000,"post":{"tiktok_post_id":null,"url":"https://www.instagram.com/p/C1LKkLdPICO","post_user_id":"5a3f8fecedc2956dd5bb6ff0","channel":"instagram","author":"priyankachopra","created_at":"2023-12-22T23:53:20+00:00","title":"Lately🙏🏽","image_url":"https://scontent-sea1-1.cdninstagram.com/v/t39.30808-6/412870692_18425453866041483_5890706475604784047_n.jpg?_nc_cat=1&ccb=1-7&_nc_sid=18de74&_nc_ohc=f48Q-GYRLJMAX8Mm1HG&_nc_ht=scontent-sea1-1.cdninstagram.com&edm=AL-3X8kEAAAA&oh=00_AfBtex7uCijhAL1ZjvjanzO2UhkveaMnWVjNB2bqy3DUpw&oe=660BB66C","avatar":"https://scontent-sea1-1.xx.fbcdn.net/v/t51.2885-15/384293351_1081650986155780_5846010834968574051_n.jpg?_nc_cat=1&ccb=1-7&_nc_sid=7d201b&_nc_ohc=h5XIkVNDwZcAX9WKlPm&_nc_ht=scontent-sea1-1.xx&edm=AL-3X8kEAAAA&oh=00_AfC4i-wcCduMRiZowfLg2Kr3sbEV1RZDECuWgYvYPQMfIA&oe=66042F32","content":null,"likes":2418089,"comments":6534,"is_business":true,"clean":true,"album":["https://instagram.fsgn5-9.fna.fbcdn.net/v/t39.30808-6/412870692_18425453866041483_5890706475604784047_n.jpg?stp=dst-jpg_e35_p1080x1080_sh0.08&_nc_ht=instagram.fsgn5-9.fna.fbcdn.net&_nc_cat=1&_nc_ohc=Da4lmEE__BUAX98Ayq3&edm=AABBvjUAAAAA&ccb=7-5&oh=00_AfCfm9ydApNaZ_7eGd-RnsIbSl5XMXli1B6EmsTh7WFhjg&oe=6609BC2C&_nc_sid=4f4799","https://instagram.fsgn5-12.fna.fbcdn.net/v/t39.30808-6/412247768_18425453875041483_2372926832768153744_n.jpg?stp=dst-jpg_e35_p1080x1080_sh0.08&_nc_ht=instagram.fsgn5-12.fna.fbcdn.net&_nc_cat=103&_nc_ohc=OL0vJ-RXT5wAX_Q_eal&edm=AABBvjUAAAAA&ccb=7-5&oh=00_AfDh97hBDPKgMgjnPbowpT8uHn50AW_BYM-0igFQ6gT_-g&oe=660AC0FE&_nc_sid=4f4799","https://instagram.fsgn5-12.fna.fbcdn.net/v/t39.30808-6/412300880_18425453884041483_3731087172702852506_n.jpg?stp=dst-jpg_e35_p1080x1080_sh0.08&_nc_ht=instagram.fsgn5-12.fna.fbcdn.net&_nc_cat=103&_nc_ohc=1g5L_wepgaYAX8S2HLS&edm=AABBvjUAAAAA&ccb=7-5&oh=00_AfC2OxaXT-1_mDNCwZpvIMFAaMWLFQOAsM75xKf8P4gcbg&oe=66093F56&_nc_sid=4f4799","https://instagram.fsgn5-12.fna.fbcdn.net/v/t39.30808-6/412702872_18425453896041483_2790065117011636838_n.jpg?stp=dst-jpg_e35_p1080x1080_sh0.08&_nc_ht=instagram.fsgn5-12.fna.fbcdn.net&_nc_cat=103&_nc_ohc=wmu6vQe4hOQAX--aaMk&edm=AABBvjUAAAAA&ccb=7-5&oh=00_AfD1vLGitLr2UMYu46StMRfFM8OIGr-X9xHqER7r-G2eoA&oe=6609A765&_nc_sid=4f4799","https://instagram.fsgn5-12.fna.fbcdn.net/v/t39.30808-6/412743891_18425453905041483_7367693909044211068_n.jpg?stp=dst-jpg_e35_p1080x1080_sh0.08&_nc_ht=instagram.fsgn5-12.fna.fbcdn.net&_nc_cat=103&_nc_ohc=vyBHWOkxGYAAX86o48w&edm=AABBvjUAAAAA&ccb=7-5&oh=00_AfAaO-vG_HES44xlFHr4YOdnIyRTwH9uWd9Gbc9yw_un9w&oe=6609E57F&_nc_sid=4f4799","https://instagram.fsgn5-12.fna.fbcdn.net/v/t39.30808-6/412802979_18425453914041483_1800121425120567190_n.jpg?stp=dst-jpg_e35_p1080x1080_sh0.08&_nc_ht=instagram.fsgn5-12.fna.fbcdn.net&_nc_cat=103&_nc_ohc=0M9ol8dqCawAX9jxH9q&edm=AABBvjUAAAAA&ccb=7-5&oh=00_AfA2oSI93JPb7KoUh9_6SuFwEheZ-6xZbBNKCt0-9ULyAg&oe=66093375&_nc_sid=4f4799","https://instagram.fsgn5-12.fna.fbcdn.net/v/t39.30808-6/412307133_18425453923041483_5455446059398783060_n.jpg?stp=dst-jpg_e35_p1080x1080_sh0.08&_nc_ht=instagram.fsgn5-12.fna.fbcdn.net&_nc_cat=103&_nc_ohc=PPIqi7U0mM0AX8xa25p&edm=AABBvjUAAAAA&ccb=7-5&oh=00_AfCPGpy6gK_8XrooDOxSiq-0a-p_KXU1nQ_DVRU06Ws9BQ&oe=660A7F21&_nc_sid=4f4799","https://instagram.fsgn5-12.fna.fbcdn.net/v/t39.30808-6/412730576_18425453932041483_5877132798139962615_n.jpg?stp=dst-jpg_e35_p1080x1080_sh0.08&_nc_ht=instagram.fsgn5-12.fna.fbcdn.net&_nc_cat=103&_nc_ohc=7wvcwr-qTT8AX_XxGxa&edm=AABBvjUAAAAA&ccb=7-5&oh=00_AfBUCv3LHbCL5z1tYqPM0qlwVf7ABrQbahuv4NYi9jLnLg&oe=66097C81&_nc_sid=4f4799"],"is_album":true,"album_video":["","","","","","","",""],"last_update_time":"2024-03-28T05:55:32.436843","followers":90801455,"max_price":109196,"min_price":107942,"location_name":"","location_public":false,"is_video":false,"location_slug":"","location_id":""}},{"date":1704067200000,"post":{"tiktok_post_id":null,"url":"https://www.instagram.com/p/C1xJjzxJ1Wm","post_user_id":"5a3f8fecedc2956dd5bb6ff0","channel":"instagram","author":"priyankachopra","created_at":"2024-01-06T17:55:41+00:00","title":"Took some time to feed my soul. 2023 had me spent.. maybe I still am. Here’s to a 2024 highlighted by peace, respite, family, love, joy and community. Hold your loved ones close. We are very lucky if we can. Happy new year ❤️🙏🏽","image_url":"https://scontent-sea1-1.cdninstagram.com/v/t39.30808-6/417744001_18428336275041483_1985164618939307511_n.jpg?_nc_cat=105&ccb=1-7&_nc_sid=18de74&_nc_ohc=Pj9hBlA8q4AAX9XeKk9&_nc_ht=scontent-sea1-1.cdninstagram.com&edm=AL-3X8kEAAAA&oh=00_AfB0kpbyfM4b7CWQF6FHyemGF21GhB6fFhv3JzTBCgTNNw&oe=660BA51D","avatar":"https://scontent-sea1-1.xx.fbcdn.net/v/t51.2885-15/384293351_1081650986155780_5846010834968574051_n.jpg?_nc_cat=1&ccb=1-7&_nc_sid=7d201b&_nc_ohc=h5XIkVNDwZcAX9WKlPm&_nc_ht=scontent-sea1-1.xx&edm=AL-3X8kEAAAA&oh=00_AfC4i-wcCduMRiZowfLg2Kr3sbEV1RZDECuWgYvYPQMfIA&oe=66042F32","content":null,"likes":4945890,"comments":7210,"is_business":true,"clean":true,"album":["https://instagram.fabb1-2.fna.fbcdn.net/v/t39.30808-6/417744001_18428336275041483_1985164618939307511_n.jpg?stp=dst-jpg_e35_p1080x1080_sh0.08&_nc_ht=instagram.fabb1-2.fna.fbcdn.net&_nc_cat=1&_nc_ohc=KOVmbOOe9wUAX9nKwm1&edm=AABBvjUAAAAA&ccb=7-5&oh=00_AfBh0A-R0gy8kmT5A9yGSU7PNc4iB4dLQ1K2h9SUREQJ-Q&oe=6609AADD&_nc_sid=4f4799","https://instagram.fabb1-1.fna.fbcdn.net/v/t51.29350-15/417203956_1459126464986179_5174297221153175512_n.jpg?stp=dst-jpg_e15_fr_p1080x1080&_nc_ht=instagram.fabb1-1.fna.fbcdn.net&_nc_cat=107&_nc_ohc=DkwtY0RVn54AX_XTFQy&edm=AABBvjUBAAAA&ccb=7-5&oh=00_AfDeNzajBqxXFXtMgHGTu83HWArzfsQ5v7lrU6KFJjIQNg&oe=6606927F&_nc_sid=4f4799","https://instagram.fabb1-1.fna.fbcdn.net/v/t39.30808-6/417133412_18428336284041483_453044396895867473_n.jpg?stp=dst-jpg_e35_p1080x1080_sh0.08&_nc_ht=instagram.fabb1-1.fna.fbcdn.net&_nc_cat=103&_nc_ohc=uAGCW84eHf8AX9_JinP&edm=AABBvjUAAAAA&ccb=7-5&oh=00_AfAM6Hp6Exqbi7HjarwsJcAjW3GGINqP2voWneTDe3cykA&oe=660A3798&_nc_sid=4f4799","https://instagram.fabb1-1.fna.fbcdn.net/v/t39.30808-6/417148863_18428336293041483_3065066976702509544_n.jpg?stp=dst-jpg_e35_p1080x1080_sh0.08&_nc_ht=instagram.fabb1-1.fna.fbcdn.net&_nc_cat=103&_nc_ohc=AAG4ffp2dVoAX_Te_HW&edm=AABBvjUAAAAA&ccb=7-5&oh=00_AfAC5e4tF90_u8lwQ_N1fmPd7OAItl7AOh8AtBffNAkrvg&oe=66092B80&_nc_sid=4f4799","https://instagram.fabb1-1.fna.fbcdn.net/v/t39.30808-6/417711279_18428336311041483_4788229091228862556_n.jpg?stp=dst-jpg_e35_p1080x1080_sh0.08&_nc_ht=instagram.fabb1-1.fna.fbcdn.net&_nc_cat=103&_nc_ohc=BtKEr3ZFzbQAX9n2wm2&edm=AABBvjUAAAAA&ccb=7-5&oh=00_AfA-bt_UIBow5odWJUZWaKDfM-Ar1LPJMKyu5MYqa3OCtQ&oe=66097C23&_nc_sid=4f4799","https://instagram.fabb1-1.fna.fbcdn.net/v/t39.30808-6/417751324_18428336320041483_1113549534419281688_n.jpg?stp=dst-jpg_e35_p1080x1080_sh0.08&_nc_ht=instagram.fabb1-1.fna.fbcdn.net&_nc_cat=103&_nc_ohc=YQZOHJ1EBx0AX8kmnEU&edm=AABBvjUAAAAA&ccb=7-5&oh=00_AfDou71PcbwVX5UaPZnE8E3pGXW-vzebexfKbJeUJGgY5g&oe=66098F55&_nc_sid=4f4799","https://instagram.fabb1-1.fna.fbcdn.net/v/t39.30808-6/417732446_18428336302041483_3555191955382421215_n.jpg?stp=dst-jpg_e35_p1080x1080_sh0.08&_nc_ht=instagram.fabb1-1.fna.fbcdn.net&_nc_cat=103&_nc_ohc=jZW0uMXSU1MAX85277Z&edm=AABBvjUAAAAA&ccb=7-5&oh=00_AfCpLYL7DjctdUVXZfSfOI8qnrhx6B2F9zglF7AUaIJlHA&oe=660A40B2&_nc_sid=4f4799","https://instagram.fabb1-1.fna.fbcdn.net/v/t39.30808-6/417694296_18428336329041483_3507181939345077520_n.jpg?stp=dst-jpg_e35_p1080x1080_sh0.08&_nc_ht=instagram.fabb1-1.fna.fbcdn.net&_nc_cat=103&_nc_ohc=UylPo8zR5_MAX8sSjza&edm=AABBvjUAAAAA&ccb=7-5&oh=00_AfAw6f2eXluPCkCtzNV-DOa-H0i8nyySGjskHNXlVWMlMQ&oe=660AE74A&_nc_sid=4f4799","https://instagram.fabb1-1.fna.fbcdn.net/v/t39.30808-6/415436425_18428336341041483_3179834357695678063_n.jpg?stp=dst-jpg_e35_p1080x1080_sh0.08&_nc_ht=instagram.fabb1-1.fna.fbcdn.net&_nc_cat=103&_nc_ohc=aXrh_dF7nvQAX-PiBLv&edm=AABBvjUAAAAA&ccb=7-5&oh=00_AfCNGjbe2-u0_axgfsttESOcH5pmSyNVyLR8QYugQZf2bQ&oe=660A7D27&_nc_sid=4f4799","https://instagram.fabb1-2.fna.fbcdn.net/v/t51.29350-15/416668185_1424496561530208_3709880767378786079_n.jpg?stp=dst-jpg_e15&_nc_ht=instagram.fabb1-2.fna.fbcdn.net&_nc_cat=100&_nc_ohc=RXdm8EqwZyIAX-Ih_NB&edm=AABBvjUBAAAA&ccb=7-5&oh=00_AfAdpVNN7z3TvjGpTCnTrOtor7oKbmGvTYor0b0aVQa-pA&oe=6606DA29&_nc_sid=4f4799"],"is_album":true,"album_video":["","https://instagram.fabb1-2.fna.fbcdn.net/v/t66.30100-16/318840291_683994677272020_8214825373666088580_n.mp4?_nc_ht=instagram.fabb1-2.fna.fbcdn.net&_nc_cat=100&_nc_ohc=lql_ZITu0SIAX-BLhdt&edm=AABBvjUBAAAA&ccb=7-5&oh=00_AfAYZ74YekhWhdHD3GGgYJx1Sf9A0JrFunYhjZU9Lf-ZKg&oe=6606F510&_nc_sid=4f4799","","","","","","","","https://instagram.fabb1-1.fna.fbcdn.net/v/t50.2886-16/416699590_2134788163545428_2251616951448043003_n.mp4?_nc_ht=instagram.fabb1-1.fna.fbcdn.net&_nc_cat=108&_nc_ohc=DUT-QLwS45IAX9C3WyX&edm=AABBvjUBAAAA&ccb=7-5&oh=00_AfDDhj7iKfvnRbugtUrk7hny-7YR1sfAXo3GNd2qlWFadw&oe=66069D6A&_nc_sid=4f4799"],"last_update_time":"2024-03-28T05:55:25.852741","followers":90801455,"max_price":109196,"min_price":107942,"location_name":"Cabo San Lucas,Mexico","location_public":true,"is_video":false,"location_slug":"cabo-san-lucasmexico","location_id":"713809241"}},{"date":1706745600000,"post":{"tiktok_post_id":null,"url":"https://www.instagram.com/p/C30orC-P6KT","post_user_id":"5a3f8fecedc2956dd5bb6ff0","channel":"instagram","author":"priyankachopra","created_at":"2024-02-26T19:28:03+00:00","title":"Time really flies. 😇🙏🏽🥹 starting the week right. #mondaymusings #nostalgia","image_url":"https://scontent-sea1-1.cdninstagram.com/v/t39.30808-6/428683870_18437397439041483_1349680213120084627_n.jpg?_nc_cat=1&ccb=1-7&_nc_sid=18de74&_nc_ohc=3mxuLHSDw80AX-CMzgR&_nc_ht=scontent-sea1-1.cdninstagram.com&edm=AL-3X8kEAAAA&oh=00_AfAMbbktpxhgkAsAbm6NTmSYPpAOKFvhZQa9uoML17tOKw&oe=660C5D30","avatar":"https://scontent-sea1-1.xx.fbcdn.net/v/t51.2885-15/384293351_1081650986155780_5846010834968574051_n.jpg?_nc_cat=1&ccb=1-7&_nc_sid=7d201b&_nc_ohc=h5XIkVNDwZcAX9WKlPm&_nc_ht=scontent-sea1-1.xx&edm=AL-3X8kEAAAA&oh=00_AfC4i-wcCduMRiZowfLg2Kr3sbEV1RZDECuWgYvYPQMfIA&oe=66042F32","content":null,"is_album":true,"likes":1180694,"comments":2697,"is_business":true,"album_video":["",""],"album":["https://scontent-sea1-1.cdninstagram.com/v/t39.30808-6/428683870_18437397439041483_1349680213120084627_n.jpg?stp=dst-jpg_e35_p1080x1080_sh0.08&_nc_ht=scontent-sea1-1.cdninstagram.com&_nc_cat=1&_nc_ohc=4rRZAgmnBFIAX_xEgJ2&edm=AABBvjUAAAAA&ccb=7-5&oh=00_AfC_I9TW2vjfrTksSuhYocKG6Gx92Cug0BlZ_IukloIYbQ&oe=660A62F0&_nc_sid=4f4799","https://scontent-sea1-1.cdninstagram.com/v/t39.30808-6/428668510_18437397418041483_8731508649232168623_n.jpg?stp=dst-jpg_e15&_nc_ht=scontent-sea1-1.cdninstagram.com&_nc_cat=103&_nc_ohc=iikGJBPjESMAX_5ZxpC&edm=AABBvjUAAAAA&ccb=7-5&oh=00_AfDwWtH5fZI9_sDToRgxZpoGtjItPhfT5GsshEg3VuZCBg&oe=6609E1F9&_nc_sid=4f4799"],"clean":true,"last_update_time":"2024-03-28T05:56:56.851916","followers":90801455,"max_price":109196,"min_price":107942,"location_name":"","location_public":false,"is_video":false,"location_slug":"","location_id":""}},{"date":1709251200000,"post":{"tiktok_post_id":null,"url":"https://www.instagram.com/p/C4-K3hcu-Hk","post_user_id":"5a3f8fecedc2956dd5bb6ff0","channel":"instagram","author":"priyankachopra","created_at":"2024-03-26T08:51:25+00:00","title":"Holi was lit. Thank you tam2cul sudeepdutt for creating such a warm atmosphere for our family! So much fun. 🤩","image_url":"https://scontent-sea1-1.cdninstagram.com/v/t39.30808-6/433738644_18446155111041483_4123773095557457348_n.jpg?_nc_cat=1&ccb=1-7&_nc_sid=18de74&_nc_ohc=lxYFE-xnUc8AX9BFfV6&_nc_ht=scontent-sea1-1.cdninstagram.com&edm=AL-3X8kEAAAA&oh=00_AfCHsk7xdhNuwPSXcU0dg2Mwta14x8hB4IhFGzo4HqMz9w&oe=660B8927","avatar":"https://scontent-sea1-1.xx.fbcdn.net/v/t51.2885-15/384293351_1081650986155780_5846010834968574051_n.jpg?_nc_cat=1&ccb=1-7&_nc_sid=7d201b&_nc_ohc=h5XIkVNDwZcAX9WKlPm&_nc_ht=scontent-sea1-1.xx&edm=AL-3X8kEAAAA&oh=00_AfC4i-wcCduMRiZowfLg2Kr3sbEV1RZDECuWgYvYPQMfIA&oe=66042F32","content":null,"is_album":true,"likes":3916728,"comments":5103,"is_business":true,"album_video":["","","https://instagram.flpb2-2.fna.fbcdn.net/v/t66.30100-16/323378466_1665165340976413_7643913409656256333_n.mp4?_nc_ht=instagram.flpb2-2.fna.fbcdn.net&_nc_cat=101&_nc_ohc=UkOllyx42cAAX9JfhiI&edm=AABBvjUBAAAA&ccb=7-5&oh=00_AfBpy71R2p4JakzP_FBVZMwPHztowypbHilNPKwjOeXpTQ&oe=6606E764&_nc_sid=4f4799","https://instagram.flpb2-1.fna.fbcdn.net/v/t66.30100-16/54647453_939173031173168_5123342043866115902_n.mp4?_nc_ht=instagram.flpb2-1.fna.fbcdn.net&_nc_cat=108&_nc_ohc=Xxw2vg8zYiQAX-PY_J8&edm=AABBvjUBAAAA&ccb=7-5&oh=00_AfC5LR2GVLw16TdVn1wLlHYMhG9Wu_LMwzm5jdWG7zUQkQ&oe=6606D824&_nc_sid=4f4799","https://instagram.flpb2-2.fna.fbcdn.net/v/t66.30100-16/317311913_221851344349071_4336236292683745024_n.mp4?_nc_ht=instagram.flpb2-2.fna.fbcdn.net&_nc_cat=103&_nc_ohc=7IYaFA9-PPYAX9ySQNn&edm=AABBvjUBAAAA&ccb=7-5&oh=00_AfA5AZPsT0-MNJjAd__SKOHz0zKmMeS5tT9mOguaNi_lPg&oe=660673EF&_nc_sid=4f4799","","","https://instagram.flpb2-1.fna.fbcdn.net/v/t66.30100-16/10000000_383304894545349_1489236312087622746_n.mp4?_nc_ht=instagram.flpb2-1.fna.fbcdn.net&_nc_cat=109&_nc_ohc=qX8hVQAY0HYAX9CFZ0-&edm=AABBvjUBAAAA&ccb=7-5&oh=00_AfDI5hxjGqlBK9IhMmqlwcdQdDh9xZDLUEIMD8gFbJ-ONw&oe=660694A8&_nc_sid=4f4799",""],"album":["https://instagram.flpb2-1.fna.fbcdn.net/v/t39.30808-6/433738644_18446155111041483_4123773095557457348_n.jpg?stp=dst-jpg_e35_p1080x1080_sh0.08&_nc_ht=instagram.flpb2-1.fna.fbcdn.net&_nc_cat=1&_nc_ohc=LVLrHFEGOGEAX8Whoc5&edm=AABBvjUAAAAA&ccb=7-5&oh=00_AfC5HL3fHjseBpL4jRJp52-IsgznXjqVLIukCak6Af4ifQ&oe=66098EE7&_nc_sid=4f4799","https://instagram.flpb2-1.fna.fbcdn.net/v/t39.30808-6/432876308_18446155099041483_2207440806926823208_n.jpg?stp=dst-jpg_e35_p1080x1080_sh0.08&_nc_ht=instagram.flpb2-1.fna.fbcdn.net&_nc_cat=1&_nc_ohc=DPX3bxdmleoAX8X6Zvl&edm=AABBvjUAAAAA&ccb=7-5&oh=00_AfC1jA19x14vY8BJ3cHO4pWe_L7BrirnoKZka_rPaIb83A&oe=6609FB26&_nc_sid=4f4799","https://instagram.flpb2-1.fna.fbcdn.net/v/t51.29350-15/434445110_442572638304819_934645894018411996_n.jpg?stp=dst-jpg_e15&_nc_ht=instagram.flpb2-1.fna.fbcdn.net&_nc_cat=1&_nc_ohc=QUiSI4fmI4IAX-pNe03&edm=AABBvjUBAAAA&ccb=7-5&oh=00_AfAjnZqMpbQ4Evbgze0U3pS7Nt-Rzu2fK3hac4XK9MfxCg&oe=6606DCC9&_nc_sid=4f4799","https://instagram.flpb2-1.fna.fbcdn.net/v/t51.29350-15/434465371_417708360896939_2512081561314369090_n.jpg?stp=dst-jpg_e15&_nc_ht=instagram.flpb2-1.fna.fbcdn.net&_nc_cat=1&_nc_ohc=pi1dyD1wrm4AX8xDIFy&edm=AABBvjUBAAAA&ccb=7-5&oh=00_AfB8co3ObTH8ZFtgR4CMYiwbG07-DifwWVxlmP9kO-UMCQ&oe=660684C5&_nc_sid=4f4799","https://instagram.flpb2-1.fna.fbcdn.net/v/t51.29350-15/434450049_936381444598614_5332728620011167228_n.jpg?stp=dst-jpg_e15&_nc_ht=instagram.flpb2-1.fna.fbcdn.net&_nc_cat=1&_nc_ohc=tyfFjUgAK-wAX_F64DS&edm=AABBvjUBAAAA&ccb=7-5&oh=00_AfAqQbcAQLlUPer1dLbHIXi3f3keRYLGkf4OsSSetvsB-A&oe=6606876D&_nc_sid=4f4799","https://instagram.flpb2-1.fna.fbcdn.net/v/t39.30808-6/432995759_18446155135041483_5810896605355815615_n.jpg?stp=dst-jpg_e35_p1080x1080_sh0.08&_nc_ht=instagram.flpb2-1.fna.fbcdn.net&_nc_cat=1&_nc_ohc=KtIHhEVfy1AAX-0tv9f&edm=AABBvjUAAAAA&ccb=7-5&oh=00_AfBhqgQ9xmIwArxJcwkGpaaNG0cs1-CaT_zr4iZ60YYEQw&oe=660A29C9&_nc_sid=4f4799","https://instagram.flpb2-1.fna.fbcdn.net/v/t39.30808-6/432896209_18446155150041483_1868949104465734856_n.jpg?stp=dst-jpg_e35_p1080x1080_sh0.08&_nc_ht=instagram.flpb2-1.fna.fbcdn.net&_nc_cat=1&_nc_ohc=07vJ3EsRvTIAX9-LYT5&edm=AABBvjUAAAAA&ccb=7-5&oh=00_AfAyGCUYbXAwZbRv20bQ66Yph8D5N03iTqyfF-JrbAiEzg&oe=660945E0&_nc_sid=4f4799","https://instagram.flpb2-1.fna.fbcdn.net/v/t51.29350-15/434462192_326902900392495_2267940648965449008_n.jpg?stp=dst-jpg_e15&_nc_ht=instagram.flpb2-1.fna.fbcdn.net&_nc_cat=1&_nc_ohc=64C-KFI2vtgAX8a-LV0&edm=AABBvjUBAAAA&ccb=7-5&oh=00_AfDhFIhQ0Q04oAkyrlWHYy3ONb3HpYYAIUPQxKrbi0XLNQ&oe=6606E425&_nc_sid=4f4799","https://instagram.flpb2-2.fna.fbcdn.net/v/t39.30808-6/432991490_18446155126041483_1473408668309610933_n.jpg?stp=dst-jpg_e35_p1080x1080_sh0.08&_nc_ht=instagram.flpb2-2.fna.fbcdn.net&_nc_cat=103&_nc_ohc=afGjwQ5SkYUAX8dZhpW&edm=AABBvjUAAAAA&ccb=7-5&oh=00_AfAbkz2Pub06o991DTXhAF0onFgY0tVNY2J6qShb--2wPw&oe=660A6ACD&_nc_sid=4f4799"],"clean":true,"last_update_time":"2024-03-28T05:57:40.633529","followers":90801455,"max_price":109196,"min_price":107942,"location_name":"Noida","location_public":true,"is_video":false,"location_slug":"noida","location_id":"787222756"}}]}